{
  "dataset": "official-liaoning-control-lines-2026-import",
  "generatedAt": "2026-07-16T18:45:00.000Z",
  "scope": {
    "province": "辽宁",
    "year": 2026,
    "sourceKind": "official-content-mirror-control-lines"
  },
  "notes": [
    "辽宁2026普通历史本科/专科442/150分、物理本科/专科344/150分共4条进入普通资格路由。",
    "特殊类型2条、体育2条和艺术8条共12条保持 special-path-only。",
    "体育和艺术10条只保存文化线与专业资格要求；本源未公开专业数值门槛，不补造专业分。",
    "既有1076条辽宁普通类官方PDF位次保留原值，本轮复核库存、端点、宽度和连续性并补齐科类PDF URL；原站直连当前超时，由省教育厅正式转载索引确认附件身份。"
  ],
  "sourceNotes": [
    {
      "id": "official-liaoning-control-lines-2026",
      "province": "辽宁",
      "title": "辽宁省2026年普通高等学校招生文化课录取控制分数线",
      "publisher": "辽宁省教育厅（文章来源：辽宁招生考试之窗）",
      "publishedAt": "2026-06-24",
      "url": "https://jyt.ln.gov.cn/jyt/jyzx/jyyw/2026063013492555300/index.shtml",
      "relatedUrls": [
        "https://gaokao.chsi.com.cn/gkxx/zc/ss/202606/20260625/2293845433.html",
        "https://jyt.ln.gov.cn/jyt/jyzx/jyyw/2026063014014729932/index.shtml",
        "https://gaokao.chsi.com.cn/gkxx/zc/ss/202606/20260625/2293847495.html",
        "https://www.lnzsks.com/newsinfo/IMS_20260624_46117_xCuXJ7lN6W.htm",
        "https://www.lnzsks.com/lnzkbfiles/2026/lns2026gkcjtjb0624clhptlw02.pdf",
        "https://www.lnzsks.com/lnzkbfiles/2026/lns2026gkcjtjb0624clhptll01.pdf"
      ],
      "quality": "official-content-mirror-liaoning-education-government-and-chsi-verified",
      "usage": "抽取辽宁2026普通、特殊类型、体育和艺术文化控制线16条；仅4条普通类本专科记录参与普通考生资格路由。",
      "parsedRecords": 16,
      "scoreMaximum": 750,
      "originalPublisher": "辽宁招生考试之窗",
      "directOriginalRetrievalStatus": "timed-out-current-session",
      "directOriginalBoundary": "辽宁招生考试之窗控制线原文与两份位次PDF本轮直连超时；不宣称已重新下载原站正文或PDF。控制线由辽宁省教育厅正式转载页与阳光高考转载页双源一致确认，位次附件身份由辽宁省教育厅正式转载索引确认。",
      "evidence": {
        "governmentControlPage": {
          "file": "official-government-control-lines.html",
          "bytes": 40803,
          "sha256": "78342d9274cee339f8fc25252f9de9bb745c93d8a96565553c360df1ce9cfd45"
        },
        "governmentRankIndex": {
          "file": "official-government-rank-index.html",
          "bytes": 37631,
          "sha256": "3dcb7f67183aa319696596cb99dead220bbb58187a10a1303eed278ab932cac4"
        },
        "chsiControlPage": {
          "file": "chsi-control-lines.html",
          "bytes": 46105,
          "sha256": "80c539ebaef02e2c09bc177910179bc8d72fa7cfe8b393237d8e6d27e1ba570d"
        },
        "chsiRankIndex": {
          "file": "chsi-rank-index.html",
          "bytes": 46212,
          "sha256": "01a89ee35cf85f4f35a8ea60e58757e40bc40853c050d2927c708bed6a79420e"
        }
      },
      "rankEvidence": {
        "sourceId": "official-liaoning-rank-2026",
        "records": 1076,
        "originalPageUrl": "https://www.lnzsks.com/newsinfo/IMS_20260624_46117_xCuXJ7lN6W.htm",
        "governmentMirrorIndexUrl": "https://jyt.ln.gov.cn/jyt/jyzx/jyyw/2026063014014729932/index.shtml",
        "historyUrl": "https://www.lnzsks.com/lnzkbfiles/2026/lns2026gkcjtjb0624clhptlw02.pdf",
        "physicsUrl": "https://www.lnzsks.com/lnzkbfiles/2026/lns2026gkcjtjb0624clhptll01.pdf",
        "inventoryAndContinuityCheck": [
          {
            "subjectType": "历史类",
            "rowsInventoryChecked": 518,
            "scoreMin": 150,
            "scoreMax": 672,
            "topRank": 12,
            "finalCumulative": 52453,
            "officialZeroPersonScoreGapsRetained": 3,
            "valueDifferences": 0,
            "rankRowsNeedingSourceUrlOnV3299Base": 518
          },
          {
            "subjectType": "物理类",
            "rowsInventoryChecked": 558,
            "scoreMin": 150,
            "scoreMax": 708,
            "topRank": 10,
            "finalCumulative": 141691,
            "officialZeroPersonScoreGapsRetained": 1,
            "valueDifferences": 0,
            "rankRowsNeedingSourceUrlOnV3299Base": 558
          }
        ],
        "valueChanges": 0,
        "controlBoundaryCrossCheck": {
          "history": {
            "vocationalScore": 150,
            "vocationalRankEnd": 52453,
            "bachelorScore": 442,
            "bachelorRankEnd": 24410,
            "specialScore": 527,
            "specialRankEnd": 10124
          },
          "physics": {
            "vocationalScore": 150,
            "vocationalRankEnd": 141691,
            "bachelorScore": 344,
            "bachelorRankEnd": 119069,
            "specialScore": 508,
            "specialRankEnd": 49824
          }
        }
      },
      "evidenceBoundary": "control-line-only=4; special-path-only=12; sports/art culture-only qualification rows=10; numeric professional thresholds=0; ordinary rank rows=1076 official PDF identities confirmed by government mirror, runtime inventory/continuity checked and values unchanged; not institution, major or admission probability"
    }
  ],
  "records": [
    {
      "id": "2026-liaoning-control-9985dca5a9e4863780",
      "province": "辽宁",
      "year": 2026,
      "subjectType": "历史类",
      "batch": "普通类本科控制分数线",
      "schoolName": "辽宁省2026年普通高等学校招生文化课录取控制分数线",
      "schoolTags": [
        "辽宁官方内容镜像控制线",
        "普通类",
        "普通类",
        "本科"
      ],
      "city": "辽宁",
      "dataType": "control-line",
      "majorName": "普通类本科控制分数线",
      "majorGroup": "普通类",
      "minScore": 442,
      "cultureScoreLine": 442,
      "scoreDimension": "total-score",
      "scoreBasis": "gaokao-total",
      "scoreMaximum": 750,
      "rankUnavailable": true,
      "scoreOnly": true,
      "sourceId": "official-liaoning-control-lines-2026",
      "sourceQuality": "official-content-mirror-liaoning-education-government-and-chsi-verified",
      "sourceUrl": "https://jyt.ln.gov.cn/jyt/jyzx/jyyw/2026063013492555300/index.shtml",
      "formalScoreScope": "control-line-only",
      "controlLineRouteKind": "ordinary-bachelor",
      "controlLineKind": "普通类本科控制分数线",
      "controlLineSection": "本科",
      "cautions": [
        "这是辽宁省2026年普通类历史类本科文化课控制分数线，只用于判断对应普通批次基本资格边界。",
        "控制线不是院校或专业投档线、录取最低分、最低位次或录取概率。"
      ],
      "sourceFile": "data/admissions/raw/liaoning-2026/official-government-control-lines.html",
      "sourcePublishedAt": "2026-06-24"
    },
    {
      "id": "2026-liaoning-control-f0cb6387a8adc964f3",
      "province": "辽宁",
      "year": 2026,
      "subjectType": "历史类",
      "batch": "普通类专科（高职、提前专科）控制分数线",
      "schoolName": "辽宁省2026年普通高等学校招生文化课录取控制分数线",
      "schoolTags": [
        "辽宁官方内容镜像控制线",
        "普通类",
        "普通类",
        "专科（高职、提前专科）"
      ],
      "city": "辽宁",
      "dataType": "control-line",
      "majorName": "普通类专科（高职、提前专科）控制分数线",
      "majorGroup": "普通类",
      "minScore": 150,
      "cultureScoreLine": 150,
      "scoreDimension": "total-score",
      "scoreBasis": "gaokao-total",
      "scoreMaximum": 750,
      "rankUnavailable": true,
      "scoreOnly": true,
      "sourceId": "official-liaoning-control-lines-2026",
      "sourceQuality": "official-content-mirror-liaoning-education-government-and-chsi-verified",
      "sourceUrl": "https://jyt.ln.gov.cn/jyt/jyzx/jyyw/2026063013492555300/index.shtml",
      "formalScoreScope": "control-line-only",
      "controlLineRouteKind": "ordinary-vocational",
      "controlLineKind": "普通类专科（高职、提前专科）控制分数线",
      "controlLineSection": "专科（高职、提前专科）",
      "cautions": [
        "这是辽宁省2026年普通类历史类专科（高职、提前专科）文化课控制分数线，只用于判断对应普通批次基本资格边界。",
        "控制线不是院校或专业投档线、录取最低分、最低位次或录取概率。"
      ],
      "sourceFile": "data/admissions/raw/liaoning-2026/official-government-control-lines.html",
      "sourcePublishedAt": "2026-06-24"
    },
    {
      "id": "2026-liaoning-control-9bb084ae0f6fe4f6ab",
      "province": "辽宁",
      "year": 2026,
      "subjectType": "物理类",
      "batch": "普通类本科控制分数线",
      "schoolName": "辽宁省2026年普通高等学校招生文化课录取控制分数线",
      "schoolTags": [
        "辽宁官方内容镜像控制线",
        "普通类",
        "普通类",
        "本科"
      ],
      "city": "辽宁",
      "dataType": "control-line",
      "majorName": "普通类本科控制分数线",
      "majorGroup": "普通类",
      "minScore": 344,
      "cultureScoreLine": 344,
      "scoreDimension": "total-score",
      "scoreBasis": "gaokao-total",
      "scoreMaximum": 750,
      "rankUnavailable": true,
      "scoreOnly": true,
      "sourceId": "official-liaoning-control-lines-2026",
      "sourceQuality": "official-content-mirror-liaoning-education-government-and-chsi-verified",
      "sourceUrl": "https://jyt.ln.gov.cn/jyt/jyzx/jyyw/2026063013492555300/index.shtml",
      "formalScoreScope": "control-line-only",
      "controlLineRouteKind": "ordinary-bachelor",
      "controlLineKind": "普通类本科控制分数线",
      "controlLineSection": "本科",
      "cautions": [
        "这是辽宁省2026年普通类物理类本科文化课控制分数线，只用于判断对应普通批次基本资格边界。",
        "控制线不是院校或专业投档线、录取最低分、最低位次或录取概率。"
      ],
      "sourceFile": "data/admissions/raw/liaoning-2026/official-government-control-lines.html",
      "sourcePublishedAt": "2026-06-24"
    },
    {
      "id": "2026-liaoning-control-485700e958845b1790",
      "province": "辽宁",
      "year": 2026,
      "subjectType": "物理类",
      "batch": "普通类专科（高职、提前专科）控制分数线",
      "schoolName": "辽宁省2026年普通高等学校招生文化课录取控制分数线",
      "schoolTags": [
        "辽宁官方内容镜像控制线",
        "普通类",
        "普通类",
        "专科（高职、提前专科）"
      ],
      "city": "辽宁",
      "dataType": "control-line",
      "majorName": "普通类专科（高职、提前专科）控制分数线",
      "majorGroup": "普通类",
      "minScore": 150,
      "cultureScoreLine": 150,
      "scoreDimension": "total-score",
      "scoreBasis": "gaokao-total",
      "scoreMaximum": 750,
      "rankUnavailable": true,
      "scoreOnly": true,
      "sourceId": "official-liaoning-control-lines-2026",
      "sourceQuality": "official-content-mirror-liaoning-education-government-and-chsi-verified",
      "sourceUrl": "https://jyt.ln.gov.cn/jyt/jyzx/jyyw/2026063013492555300/index.shtml",
      "formalScoreScope": "control-line-only",
      "controlLineRouteKind": "ordinary-vocational",
      "controlLineKind": "普通类专科（高职、提前专科）控制分数线",
      "controlLineSection": "专科（高职、提前专科）",
      "cautions": [
        "这是辽宁省2026年普通类物理类专科（高职、提前专科）文化课控制分数线，只用于判断对应普通批次基本资格边界。",
        "控制线不是院校或专业投档线、录取最低分、最低位次或录取概率。"
      ],
      "sourceFile": "data/admissions/raw/liaoning-2026/official-government-control-lines.html",
      "sourcePublishedAt": "2026-06-24"
    },
    {
      "id": "2026-liaoning-control-a2c4d1c2b4c11149b7",
      "province": "辽宁",
      "year": 2026,
      "subjectType": "历史类",
      "batch": "特殊类型招生控制分数线",
      "schoolName": "辽宁省2026年普通高等学校招生文化课录取控制分数线",
      "schoolTags": [
        "辽宁官方内容镜像控制线",
        "特殊路径",
        "特殊类型招生",
        "本科"
      ],
      "city": "辽宁",
      "dataType": "control-line",
      "majorName": "特殊类型招生控制分数线",
      "majorGroup": "特殊类型招生",
      "minScore": 527,
      "cultureScoreLine": 527,
      "scoreDimension": "total-score",
      "scoreBasis": "gaokao-total",
      "scoreMaximum": 750,
      "rankUnavailable": true,
      "scoreOnly": true,
      "sourceId": "official-liaoning-control-lines-2026",
      "sourceQuality": "official-content-mirror-liaoning-education-government-and-chsi-verified",
      "sourceUrl": "https://jyt.ln.gov.cn/jyt/jyzx/jyyw/2026063013492555300/index.shtml",
      "formalScoreScope": "special-path-only",
      "controlLineRouteKind": "special",
      "controlLineKind": "特殊类型招生控制分数线",
      "controlLineSection": "本科",
      "cautions": [
        "这是辽宁省2026年特殊类型招生控制分数线，属于特殊、体育或艺术路径，不替代普通类控制线。",
        "该记录保持 special-path-only，不进入普通类资格线或普通录取概率计算。"
      ],
      "sourceFile": "data/admissions/raw/liaoning-2026/official-government-control-lines.html",
      "sourcePublishedAt": "2026-06-24"
    },
    {
      "id": "2026-liaoning-control-431ab43033140da254",
      "province": "辽宁",
      "year": 2026,
      "subjectType": "物理类",
      "batch": "特殊类型招生控制分数线",
      "schoolName": "辽宁省2026年普通高等学校招生文化课录取控制分数线",
      "schoolTags": [
        "辽宁官方内容镜像控制线",
        "特殊路径",
        "特殊类型招生",
        "本科"
      ],
      "city": "辽宁",
      "dataType": "control-line",
      "majorName": "特殊类型招生控制分数线",
      "majorGroup": "特殊类型招生",
      "minScore": 508,
      "cultureScoreLine": 508,
      "scoreDimension": "total-score",
      "scoreBasis": "gaokao-total",
      "scoreMaximum": 750,
      "rankUnavailable": true,
      "scoreOnly": true,
      "sourceId": "official-liaoning-control-lines-2026",
      "sourceQuality": "official-content-mirror-liaoning-education-government-and-chsi-verified",
      "sourceUrl": "https://jyt.ln.gov.cn/jyt/jyzx/jyyw/2026063013492555300/index.shtml",
      "formalScoreScope": "special-path-only",
      "controlLineRouteKind": "special",
      "controlLineKind": "特殊类型招生控制分数线",
      "controlLineSection": "本科",
      "cautions": [
        "这是辽宁省2026年特殊类型招生控制分数线，属于特殊、体育或艺术路径，不替代普通类控制线。",
        "该记录保持 special-path-only，不进入普通类资格线或普通录取概率计算。"
      ],
      "sourceFile": "data/admissions/raw/liaoning-2026/official-government-control-lines.html",
      "sourcePublishedAt": "2026-06-24"
    },
    {
      "id": "2026-liaoning-control-c598e97c09d3f2d912",
      "province": "辽宁",
      "year": 2026,
      "subjectType": "历史类",
      "batch": "体育类本、专科（高职）文化成绩控制分数线",
      "schoolName": "辽宁省2026年普通高等学校招生文化课录取控制分数线",
      "schoolTags": [
        "辽宁官方内容镜像控制线",
        "特殊路径",
        "体育类",
        "本、专科（高职）"
      ],
      "city": "辽宁",
      "dataType": "control-line",
      "majorName": "体育类本、专科（高职）文化成绩控制分数线",
      "majorGroup": "体育类",
      "minScore": 150,
      "cultureScoreLine": 150,
      "professionalQualification": "体育类专业考试达到辽宁省2026年对应招生要求",
      "scoreDimension": "culture-and-qualification",
      "scoreBasis": "culture-score",
      "scoreMaximum": 750,
      "rankUnavailable": true,
      "scoreOnly": true,
      "sourceId": "official-liaoning-control-lines-2026",
      "sourceQuality": "official-content-mirror-liaoning-education-government-and-chsi-verified",
      "sourceUrl": "https://jyt.ln.gov.cn/jyt/jyzx/jyyw/2026063013492555300/index.shtml",
      "formalScoreScope": "special-path-only",
      "controlLineRouteKind": "sports",
      "controlLineKind": "体育类本、专科（高职）文化成绩控制分数线",
      "controlLineSection": "本、专科（高职）",
      "cautions": [
        "这是辽宁省2026年体育类本、专科（高职）文化成绩控制分数线，属于特殊、体育或艺术路径，不替代普通类控制线。",
        "本源只公开文化成绩控制线，专业考试合格要求须按当年政策和招生章程另行核验，不补造专业分。"
      ],
      "sourceFile": "data/admissions/raw/liaoning-2026/official-government-control-lines.html",
      "sourcePublishedAt": "2026-06-24"
    },
    {
      "id": "2026-liaoning-control-fb78a3209c74513ab4",
      "province": "辽宁",
      "year": 2026,
      "subjectType": "物理类",
      "batch": "体育类本、专科（高职）文化成绩控制分数线",
      "schoolName": "辽宁省2026年普通高等学校招生文化课录取控制分数线",
      "schoolTags": [
        "辽宁官方内容镜像控制线",
        "特殊路径",
        "体育类",
        "本、专科（高职）"
      ],
      "city": "辽宁",
      "dataType": "control-line",
      "majorName": "体育类本、专科（高职）文化成绩控制分数线",
      "majorGroup": "体育类",
      "minScore": 150,
      "cultureScoreLine": 150,
      "professionalQualification": "体育类专业考试达到辽宁省2026年对应招生要求",
      "scoreDimension": "culture-and-qualification",
      "scoreBasis": "culture-score",
      "scoreMaximum": 750,
      "rankUnavailable": true,
      "scoreOnly": true,
      "sourceId": "official-liaoning-control-lines-2026",
      "sourceQuality": "official-content-mirror-liaoning-education-government-and-chsi-verified",
      "sourceUrl": "https://jyt.ln.gov.cn/jyt/jyzx/jyyw/2026063013492555300/index.shtml",
      "formalScoreScope": "special-path-only",
      "controlLineRouteKind": "sports",
      "controlLineKind": "体育类本、专科（高职）文化成绩控制分数线",
      "controlLineSection": "本、专科（高职）",
      "cautions": [
        "这是辽宁省2026年体育类本、专科（高职）文化成绩控制分数线，属于特殊、体育或艺术路径，不替代普通类控制线。",
        "本源只公开文化成绩控制线，专业考试合格要求须按当年政策和招生章程另行核验，不补造专业分。"
      ],
      "sourceFile": "data/admissions/raw/liaoning-2026/official-government-control-lines.html",
      "sourcePublishedAt": "2026-06-24"
    },
    {
      "id": "2026-liaoning-control-46805beb0475d99c78",
      "province": "辽宁",
      "year": 2026,
      "subjectType": "历史类",
      "batch": "艺术类本科普通专业文化线",
      "schoolName": "辽宁省2026年普通高等学校招生文化课录取控制分数线",
      "schoolTags": [
        "辽宁官方内容镜像控制线",
        "特殊路径",
        "艺术类本科普通专业文化线",
        "本科"
      ],
      "city": "辽宁",
      "dataType": "control-line",
      "majorName": "艺术类本科普通专业文化线",
      "majorGroup": "艺术类本科普通专业文化线",
      "minScore": 331,
      "cultureScoreLine": 331,
      "professionalQualification": "艺术类专业考试达到辽宁省2026年对应招生要求",
      "scoreDimension": "culture-and-qualification",
      "scoreBasis": "culture-score",
      "scoreMaximum": 750,
      "rankUnavailable": true,
      "scoreOnly": true,
      "sourceId": "official-liaoning-control-lines-2026",
      "sourceQuality": "official-content-mirror-liaoning-education-government-and-chsi-verified",
      "sourceUrl": "https://jyt.ln.gov.cn/jyt/jyzx/jyyw/2026063013492555300/index.shtml",
      "formalScoreScope": "special-path-only",
      "controlLineRouteKind": "art",
      "controlLineKind": "艺术类本科普通专业文化线",
      "controlLineSection": "本科",
      "cautions": [
        "这是辽宁省2026年艺术类本科普通专业文化线，属于特殊、体育或艺术路径，不替代普通类控制线。",
        "本源只公开文化成绩控制线，专业考试合格要求须按当年政策和招生章程另行核验，不补造专业分。"
      ],
      "sourceFile": "data/admissions/raw/liaoning-2026/official-government-control-lines.html",
      "sourcePublishedAt": "2026-06-24"
    },
    {
      "id": "2026-liaoning-control-8c2c55f4645a54ab68",
      "province": "辽宁",
      "year": 2026,
      "subjectType": "历史类",
      "batch": "舞蹈、戏剧影视表演、服装表演、音乐表演文化线",
      "schoolName": "辽宁省2026年普通高等学校招生文化课录取控制分数线",
      "schoolTags": [
        "辽宁官方内容镜像控制线",
        "特殊路径",
        "舞蹈、戏剧影视表演、服装表演、音乐表演文化线",
        "本科"
      ],
      "city": "辽宁",
      "dataType": "control-line",
      "majorName": "舞蹈、戏剧影视表演、服装表演、音乐表演文化线",
      "majorGroup": "舞蹈、戏剧影视表演、服装表演、音乐表演文化线",
      "minScore": 250,
      "cultureScoreLine": 250,
      "professionalQualification": "对应艺术类专业考试达到辽宁省2026年招生要求",
      "scoreDimension": "culture-and-qualification",
      "scoreBasis": "culture-score",
      "scoreMaximum": 750,
      "rankUnavailable": true,
      "scoreOnly": true,
      "sourceId": "official-liaoning-control-lines-2026",
      "sourceQuality": "official-content-mirror-liaoning-education-government-and-chsi-verified",
      "sourceUrl": "https://jyt.ln.gov.cn/jyt/jyzx/jyyw/2026063013492555300/index.shtml",
      "formalScoreScope": "special-path-only",
      "controlLineRouteKind": "art",
      "controlLineKind": "舞蹈、戏剧影视表演、服装表演、音乐表演文化线",
      "controlLineSection": "本科",
      "cautions": [
        "这是辽宁省2026年舞蹈、戏剧影视表演、服装表演、音乐表演文化线，属于特殊、体育或艺术路径，不替代普通类控制线。",
        "本源只公开文化成绩控制线，专业考试合格要求须按当年政策和招生章程另行核验，不补造专业分。"
      ],
      "sourceFile": "data/admissions/raw/liaoning-2026/official-government-control-lines.html",
      "sourcePublishedAt": "2026-06-24"
    },
    {
      "id": "2026-liaoning-control-54e9b5362720ce6107",
      "province": "辽宁",
      "year": 2026,
      "subjectType": "历史类",
      "batch": "戏曲类专业文化线",
      "schoolName": "辽宁省2026年普通高等学校招生文化课录取控制分数线",
      "schoolTags": [
        "辽宁官方内容镜像控制线",
        "特殊路径",
        "戏曲类专业文化线",
        "本科"
      ],
      "city": "辽宁",
      "dataType": "control-line",
      "majorName": "戏曲类专业文化线",
      "majorGroup": "戏曲类专业文化线",
      "minScore": 221,
      "cultureScoreLine": 221,
      "professionalQualification": "戏曲类专业考试达到辽宁省2026年招生要求",
      "scoreDimension": "culture-and-qualification",
      "scoreBasis": "culture-score",
      "scoreMaximum": 750,
      "rankUnavailable": true,
      "scoreOnly": true,
      "sourceId": "official-liaoning-control-lines-2026",
      "sourceQuality": "official-content-mirror-liaoning-education-government-and-chsi-verified",
      "sourceUrl": "https://jyt.ln.gov.cn/jyt/jyzx/jyyw/2026063013492555300/index.shtml",
      "formalScoreScope": "special-path-only",
      "controlLineRouteKind": "art",
      "controlLineKind": "戏曲类专业文化线",
      "controlLineSection": "本科",
      "cautions": [
        "这是辽宁省2026年戏曲类专业文化线，属于特殊、体育或艺术路径，不替代普通类控制线。",
        "本源只公开文化成绩控制线，专业考试合格要求须按当年政策和招生章程另行核验，不补造专业分。"
      ],
      "sourceFile": "data/admissions/raw/liaoning-2026/official-government-control-lines.html",
      "sourcePublishedAt": "2026-06-24"
    },
    {
      "id": "2026-liaoning-control-06d070b08dfbe3e8ce",
      "province": "辽宁",
      "year": 2026,
      "subjectType": "历史类",
      "batch": "艺术类专科（高职）文化线",
      "schoolName": "辽宁省2026年普通高等学校招生文化课录取控制分数线",
      "schoolTags": [
        "辽宁官方内容镜像控制线",
        "特殊路径",
        "艺术类专科（高职）文化线",
        "专科（高职）"
      ],
      "city": "辽宁",
      "dataType": "control-line",
      "majorName": "艺术类专科（高职）文化线",
      "majorGroup": "艺术类专科（高职）文化线",
      "minScore": 150,
      "cultureScoreLine": 150,
      "professionalQualification": "艺术类专业考试达到辽宁省2026年对应招生要求",
      "scoreDimension": "culture-and-qualification",
      "scoreBasis": "culture-score",
      "scoreMaximum": 750,
      "rankUnavailable": true,
      "scoreOnly": true,
      "sourceId": "official-liaoning-control-lines-2026",
      "sourceQuality": "official-content-mirror-liaoning-education-government-and-chsi-verified",
      "sourceUrl": "https://jyt.ln.gov.cn/jyt/jyzx/jyyw/2026063013492555300/index.shtml",
      "formalScoreScope": "special-path-only",
      "controlLineRouteKind": "art",
      "controlLineKind": "艺术类专科（高职）文化线",
      "controlLineSection": "专科（高职）",
      "cautions": [
        "这是辽宁省2026年艺术类专科（高职）文化线，属于特殊、体育或艺术路径，不替代普通类控制线。",
        "本源只公开文化成绩控制线，专业考试合格要求须按当年政策和招生章程另行核验，不补造专业分。"
      ],
      "sourceFile": "data/admissions/raw/liaoning-2026/official-government-control-lines.html",
      "sourcePublishedAt": "2026-06-24"
    },
    {
      "id": "2026-liaoning-control-0a3a7d33621d319fa8",
      "province": "辽宁",
      "year": 2026,
      "subjectType": "物理类",
      "batch": "艺术类本科普通专业文化线",
      "schoolName": "辽宁省2026年普通高等学校招生文化课录取控制分数线",
      "schoolTags": [
        "辽宁官方内容镜像控制线",
        "特殊路径",
        "艺术类本科普通专业文化线",
        "本科"
      ],
      "city": "辽宁",
      "dataType": "control-line",
      "majorName": "艺术类本科普通专业文化线",
      "majorGroup": "艺术类本科普通专业文化线",
      "minScore": 258,
      "cultureScoreLine": 258,
      "professionalQualification": "艺术类专业考试达到辽宁省2026年对应招生要求",
      "scoreDimension": "culture-and-qualification",
      "scoreBasis": "culture-score",
      "scoreMaximum": 750,
      "rankUnavailable": true,
      "scoreOnly": true,
      "sourceId": "official-liaoning-control-lines-2026",
      "sourceQuality": "official-content-mirror-liaoning-education-government-and-chsi-verified",
      "sourceUrl": "https://jyt.ln.gov.cn/jyt/jyzx/jyyw/2026063013492555300/index.shtml",
      "formalScoreScope": "special-path-only",
      "controlLineRouteKind": "art",
      "controlLineKind": "艺术类本科普通专业文化线",
      "controlLineSection": "本科",
      "cautions": [
        "这是辽宁省2026年艺术类本科普通专业文化线，属于特殊、体育或艺术路径，不替代普通类控制线。",
        "本源只公开文化成绩控制线，专业考试合格要求须按当年政策和招生章程另行核验，不补造专业分。"
      ],
      "sourceFile": "data/admissions/raw/liaoning-2026/official-government-control-lines.html",
      "sourcePublishedAt": "2026-06-24"
    },
    {
      "id": "2026-liaoning-control-345e1fc3c331a59976",
      "province": "辽宁",
      "year": 2026,
      "subjectType": "物理类",
      "batch": "舞蹈、戏剧影视表演、服装表演、音乐表演文化线",
      "schoolName": "辽宁省2026年普通高等学校招生文化课录取控制分数线",
      "schoolTags": [
        "辽宁官方内容镜像控制线",
        "特殊路径",
        "舞蹈、戏剧影视表演、服装表演、音乐表演文化线",
        "本科"
      ],
      "city": "辽宁",
      "dataType": "control-line",
      "majorName": "舞蹈、戏剧影视表演、服装表演、音乐表演文化线",
      "majorGroup": "舞蹈、戏剧影视表演、服装表演、音乐表演文化线",
      "minScore": 250,
      "cultureScoreLine": 250,
      "professionalQualification": "对应艺术类专业考试达到辽宁省2026年招生要求",
      "scoreDimension": "culture-and-qualification",
      "scoreBasis": "culture-score",
      "scoreMaximum": 750,
      "rankUnavailable": true,
      "scoreOnly": true,
      "sourceId": "official-liaoning-control-lines-2026",
      "sourceQuality": "official-content-mirror-liaoning-education-government-and-chsi-verified",
      "sourceUrl": "https://jyt.ln.gov.cn/jyt/jyzx/jyyw/2026063013492555300/index.shtml",
      "formalScoreScope": "special-path-only",
      "controlLineRouteKind": "art",
      "controlLineKind": "舞蹈、戏剧影视表演、服装表演、音乐表演文化线",
      "controlLineSection": "本科",
      "cautions": [
        "这是辽宁省2026年舞蹈、戏剧影视表演、服装表演、音乐表演文化线，属于特殊、体育或艺术路径，不替代普通类控制线。",
        "本源只公开文化成绩控制线，专业考试合格要求须按当年政策和招生章程另行核验，不补造专业分。"
      ],
      "sourceFile": "data/admissions/raw/liaoning-2026/official-government-control-lines.html",
      "sourcePublishedAt": "2026-06-24"
    },
    {
      "id": "2026-liaoning-control-35439e63d0085a09a4",
      "province": "辽宁",
      "year": 2026,
      "subjectType": "物理类",
      "batch": "戏曲类专业文化线",
      "schoolName": "辽宁省2026年普通高等学校招生文化课录取控制分数线",
      "schoolTags": [
        "辽宁官方内容镜像控制线",
        "特殊路径",
        "戏曲类专业文化线",
        "本科"
      ],
      "city": "辽宁",
      "dataType": "control-line",
      "majorName": "戏曲类专业文化线",
      "majorGroup": "戏曲类专业文化线",
      "minScore": 172,
      "cultureScoreLine": 172,
      "professionalQualification": "戏曲类专业考试达到辽宁省2026年招生要求",
      "scoreDimension": "culture-and-qualification",
      "scoreBasis": "culture-score",
      "scoreMaximum": 750,
      "rankUnavailable": true,
      "scoreOnly": true,
      "sourceId": "official-liaoning-control-lines-2026",
      "sourceQuality": "official-content-mirror-liaoning-education-government-and-chsi-verified",
      "sourceUrl": "https://jyt.ln.gov.cn/jyt/jyzx/jyyw/2026063013492555300/index.shtml",
      "formalScoreScope": "special-path-only",
      "controlLineRouteKind": "art",
      "controlLineKind": "戏曲类专业文化线",
      "controlLineSection": "本科",
      "cautions": [
        "这是辽宁省2026年戏曲类专业文化线，属于特殊、体育或艺术路径，不替代普通类控制线。",
        "本源只公开文化成绩控制线，专业考试合格要求须按当年政策和招生章程另行核验，不补造专业分。"
      ],
      "sourceFile": "data/admissions/raw/liaoning-2026/official-government-control-lines.html",
      "sourcePublishedAt": "2026-06-24"
    },
    {
      "id": "2026-liaoning-control-d01d5f379dc75b45a3",
      "province": "辽宁",
      "year": 2026,
      "subjectType": "物理类",
      "batch": "艺术类专科（高职）文化线",
      "schoolName": "辽宁省2026年普通高等学校招生文化课录取控制分数线",
      "schoolTags": [
        "辽宁官方内容镜像控制线",
        "特殊路径",
        "艺术类专科（高职）文化线",
        "专科（高职）"
      ],
      "city": "辽宁",
      "dataType": "control-line",
      "majorName": "艺术类专科（高职）文化线",
      "majorGroup": "艺术类专科（高职）文化线",
      "minScore": 150,
      "cultureScoreLine": 150,
      "professionalQualification": "艺术类专业考试达到辽宁省2026年对应招生要求",
      "scoreDimension": "culture-and-qualification",
      "scoreBasis": "culture-score",
      "scoreMaximum": 750,
      "rankUnavailable": true,
      "scoreOnly": true,
      "sourceId": "official-liaoning-control-lines-2026",
      "sourceQuality": "official-content-mirror-liaoning-education-government-and-chsi-verified",
      "sourceUrl": "https://jyt.ln.gov.cn/jyt/jyzx/jyyw/2026063013492555300/index.shtml",
      "formalScoreScope": "special-path-only",
      "controlLineRouteKind": "art",
      "controlLineKind": "艺术类专科（高职）文化线",
      "controlLineSection": "专科（高职）",
      "cautions": [
        "这是辽宁省2026年艺术类专科（高职）文化线，属于特殊、体育或艺术路径，不替代普通类控制线。",
        "本源只公开文化成绩控制线，专业考试合格要求须按当年政策和招生章程另行核验，不补造专业分。"
      ],
      "sourceFile": "data/admissions/raw/liaoning-2026/official-government-control-lines.html",
      "sourcePublishedAt": "2026-06-24"
    }
  ],
  "diagnostics": {
    "recordCount": 16,
    "ordinaryRecords": 4,
    "specialPathRecords": 12,
    "professionalQualificationRecords": 10,
    "professionalNumericRecords": 0,
    "routeCounts": {
      "ordinary-bachelor": 2,
      "ordinary-vocational": 2,
      "special": 2,
      "sports": 2,
      "art": 8
    },
    "ordinaryBoundaries": {
      "historyBachelor": 442,
      "historyVocational": 150,
      "physicsBachelor": 344,
      "physicsVocational": 150
    },
    "rankRecords": 1076,
    "rankRowsInventoryChecked": 1076,
    "rankValueChanges": 0,
    "scoreMaximum": 750
  }
}
