{
  "dataset": "official-guizhou-control-lines-2026-import",
  "generatedAt": "2026-07-16T15:30:00.000Z",
  "scope": {
    "province": "贵州",
    "year": 2026,
    "sourceKind": "official-content-mirror-control-lines"
  },
  "notes": [
    "贵州2026普通类物理本科393分、专科200分，历史本科439分、专科200分进入普通资格路由。",
    "特殊类型2条、艺术18条、体育4条和民汉双语口语1条共25条保持 special-path-only。",
    "艺体页面仅公开文化控制线，22条艺体记录保留专业资格要求但不生成任何假专业分。",
    "贵州招生考试院微信公众号本轮返回环境验证页，考试院独立站TLS连接失败；控制线使用阳光高考完整转载、铜仁政府来源原图和中新网文字交叉核验，明确标注 official-content-mirror。",
    "既有1201条贵州2026官方一分一段记录不改分数和位次，本轮只补齐历史/物理对应考试院PDF URL；两份同字节镜像与既有官方PDF哈希一致。"
  ],
  "sourceNotes": [
    {
      "id": "official-guizhou-control-lines-2026",
      "province": "贵州",
      "title": "贵州省2026年高考录取控制分数线划定",
      "publisher": "贵州省招生考试院（阳光高考正式转载；铜仁政府原图与中新网交叉核验）",
      "publishedAt": "2026-06-25",
      "url": "https://gaokao.chsi.com.cn/gkxx/zc/ss/202606/20260625/2293847640.html",
      "originalOfficialUrl": "https://mp.weixin.qq.com/s/nKVg7jaelGMXD2NrAKEDAQ",
      "relatedUrls": [
        "https://www.tongren.gov.cn/2026/0626/349877.shtml",
        "https://upload.tongren.gov.cn/2026/0626/1782441098295.jpg",
        "https://www.gz.chinanews.com.cn/jjgz/2026-06-25/doc-ihfftkrx9678346.shtml",
        "https://zsksy.guizhou.gov.cn/zlxz/202606/t20260625_90556851.html",
        "https://zsksy.guizhou.gov.cn/zlxz/202606/P020260625601945966806.pdf",
        "https://zsksy.guizhou.gov.cn/zlxz/202606/P020260625601945906859.pdf",
        "https://www.jhgk.cn/upload/file/20260625/1782391200436011607.pdf",
        "https://www.jhgk.cn/upload/file/20260625/1782391176947090104.pdf"
      ],
      "quality": "official-content-mirror-guizhou-chsi-government-image-and-chinanews-verified",
      "usage": "抽取贵州2026普通类、特殊类型、艺术、体育和民汉双语口语控制线29条；仅4条普通类本专科记录参与普通考生资格路由。",
      "parsedRecords": 29,
      "scoreMaximum": 750,
      "originalWechatRetrievalStatus": "blocked-by-environment-verification",
      "officialRankSiteRedownloadStatus": "blocked-current-session-tls",
      "evidence": {
        "officialWechatBlockedPage": {
          "file": "official-wechat-control-lines.html",
          "bytes": 18165,
          "sha256": "2a9a2424eccd3c1b0e5b0e4b0ea58150020e9741409ff7a9f6d3abeab98a6e90"
        },
        "chsiControlPage": {
          "file": "chsi-control-lines.html",
          "bytes": 45328,
          "sha256": "f120e3eb02405ef70242b8936438bd8e8a24a2607ea26c4674aedfb675e7d4c6"
        },
        "chinaNewsControlPage": {
          "file": "chinanews-control-lines.html",
          "bytes": 53754,
          "sha256": "8226481d69def8df3e625227a8095ef027a40597a6dbc55186263c32dfc913b9"
        },
        "tongrenGovernmentPage": {
          "file": "tongren-government-control-lines.html",
          "bytes": 29082,
          "sha256": "3970e4b82573636e4195fdcf006c9adf58ab72e908f029bcbe7e477313a4f2c0"
        },
        "tongrenGovernmentImage": {
          "file": "tongren-government-official-content-mirror.jpg",
          "bytes": 279718,
          "width": 550,
          "height": 2305,
          "sha256": "803941857c6ba11d75791d157f1710d2b7d5855791ed188b86b79970dfad339f"
        },
        "rankHistoryIdenticalMirror": {
          "file": "rank-history-identical-mirror.pdf",
          "bytes": 310144,
          "pages": 3,
          "sha256": "0b8cf4360336c19442eab70355617624ca87d9f4f40a65b99346ff8fb798d183"
        },
        "rankPhysicsIdenticalMirror": {
          "file": "rank-physics-identical-mirror.pdf",
          "bytes": 455692,
          "pages": 3,
          "sha256": "361ae84119880307acff21018f96cd06d1c530859bf4ad6fee41f1e07099f9c4"
        }
      },
      "manualVisualVerification": {
        "verifiedAt": "2026-07-16",
        "finding": "铜仁政府转载原图清晰展示普通、艺术、体育和民汉双语口语全部控制线；逐项数值与阳光高考及中新网正文一致。"
      },
      "rankEvidence": {
        "sourceId": "official-guizhou-rank-2026",
        "records": 1201,
        "historyUrl": "https://zsksy.guizhou.gov.cn/zlxz/202606/P020260625601945966806.pdf",
        "physicsUrl": "https://zsksy.guizhou.gov.cn/zlxz/202606/P020260625601945906859.pdf",
        "historyIdenticalMirrorUrl": "https://www.jhgk.cn/upload/file/20260625/1782391200436011607.pdf",
        "physicsIdenticalMirrorUrl": "https://www.jhgk.cn/upload/file/20260625/1782391176947090104.pdf",
        "valueChanges": 0,
        "controlBoundaryCrossCheck": {
          "history": {
            "vocationalScore": 200,
            "vocationalRankEnd": 83144,
            "bachelorScore": 439,
            "bachelorRankEnd": 37867,
            "specialScore": 503,
            "specialRankEnd": 15657
          },
          "physics": {
            "vocationalScore": 200,
            "vocationalRankEnd": 212055,
            "bachelorScore": 393,
            "bachelorRankEnd": 158893,
            "specialScore": 494,
            "specialRankEnd": 66184
          }
        }
      },
      "evidenceBoundary": "control-line-only=4; special-path-only=25; art/sports culture lines=22 with professional qualification but no invented professional score; rank rows=1201 official PDF URL inventory retained and values unchanged; control source is official-content-mirror; not institution-group, institution or major admission score"
    }
  ],
  "records": [
    {
      "id": "2026-guizhou-control-e97bcdaf958828c2c8",
      "province": "贵州",
      "year": 2026,
      "subjectType": "物理类",
      "batch": "普通类本科录取控制分数线",
      "schoolName": "贵州省2026年高考录取控制分数线",
      "schoolTags": [
        "贵州官方内容镜像控制线",
        "普通类",
        "普通类",
        "本科"
      ],
      "city": "贵州",
      "dataType": "control-line",
      "majorName": "普通类本科录取控制分数线",
      "majorGroup": "普通类",
      "minScore": 393,
      "cultureScoreLine": 393,
      "scoreDimension": "total-score",
      "scoreBasis": "gaokao-total",
      "scoreMaximum": 750,
      "rankUnavailable": true,
      "scoreOnly": true,
      "sourceId": "official-guizhou-control-lines-2026",
      "sourceQuality": "official-content-mirror-guizhou-chsi-government-image-and-chinanews-verified",
      "sourceUrl": "https://gaokao.chsi.com.cn/gkxx/zc/ss/202606/20260625/2293847640.html",
      "formalScoreScope": "control-line-only",
      "controlLineRouteKind": "ordinary-bachelor",
      "controlLineKind": "普通类本科录取控制分数线",
      "controlLineSection": "本科",
      "cautions": [
        "这是贵州省2026年普通类对应首选科目本科或高职专科录取控制分数线，只用于判断基本资格边界。",
        "物理类本科393分、历史类本科439分；普通高职专科两科均为200分，必须按首选科目和批次判断。",
        "控制线不是院校专业组投档线、院校录取线、专业录取最低分或最低位次，不能单独生成录取概率。"
      ],
      "sourceFile": "data/admissions/raw/guizhou-2026/chsi-control-lines.html",
      "sourcePublishedAt": "2026-06-25"
    },
    {
      "id": "2026-guizhou-control-500a8eee1a8a4097e9",
      "province": "贵州",
      "year": 2026,
      "subjectType": "物理类",
      "batch": "普通类高职（专科）录取控制分数线",
      "schoolName": "贵州省2026年高考录取控制分数线",
      "schoolTags": [
        "贵州官方内容镜像控制线",
        "普通类",
        "普通类",
        "高职（专科）"
      ],
      "city": "贵州",
      "dataType": "control-line",
      "majorName": "普通类高职（专科）录取控制分数线",
      "majorGroup": "普通类",
      "minScore": 200,
      "cultureScoreLine": 200,
      "scoreDimension": "total-score",
      "scoreBasis": "gaokao-total",
      "scoreMaximum": 750,
      "rankUnavailable": true,
      "scoreOnly": true,
      "sourceId": "official-guizhou-control-lines-2026",
      "sourceQuality": "official-content-mirror-guizhou-chsi-government-image-and-chinanews-verified",
      "sourceUrl": "https://gaokao.chsi.com.cn/gkxx/zc/ss/202606/20260625/2293847640.html",
      "formalScoreScope": "control-line-only",
      "controlLineRouteKind": "ordinary-vocational",
      "controlLineKind": "普通类高职（专科）录取控制分数线",
      "controlLineSection": "高职（专科）",
      "cautions": [
        "这是贵州省2026年普通类对应首选科目本科或高职专科录取控制分数线，只用于判断基本资格边界。",
        "物理类本科393分、历史类本科439分；普通高职专科两科均为200分，必须按首选科目和批次判断。",
        "控制线不是院校专业组投档线、院校录取线、专业录取最低分或最低位次，不能单独生成录取概率。"
      ],
      "sourceFile": "data/admissions/raw/guizhou-2026/chsi-control-lines.html",
      "sourcePublishedAt": "2026-06-25"
    },
    {
      "id": "2026-guizhou-control-0e6e4002580cab170f",
      "province": "贵州",
      "year": 2026,
      "subjectType": "历史类",
      "batch": "普通类本科录取控制分数线",
      "schoolName": "贵州省2026年高考录取控制分数线",
      "schoolTags": [
        "贵州官方内容镜像控制线",
        "普通类",
        "普通类",
        "本科"
      ],
      "city": "贵州",
      "dataType": "control-line",
      "majorName": "普通类本科录取控制分数线",
      "majorGroup": "普通类",
      "minScore": 439,
      "cultureScoreLine": 439,
      "scoreDimension": "total-score",
      "scoreBasis": "gaokao-total",
      "scoreMaximum": 750,
      "rankUnavailable": true,
      "scoreOnly": true,
      "sourceId": "official-guizhou-control-lines-2026",
      "sourceQuality": "official-content-mirror-guizhou-chsi-government-image-and-chinanews-verified",
      "sourceUrl": "https://gaokao.chsi.com.cn/gkxx/zc/ss/202606/20260625/2293847640.html",
      "formalScoreScope": "control-line-only",
      "controlLineRouteKind": "ordinary-bachelor",
      "controlLineKind": "普通类本科录取控制分数线",
      "controlLineSection": "本科",
      "cautions": [
        "这是贵州省2026年普通类对应首选科目本科或高职专科录取控制分数线，只用于判断基本资格边界。",
        "物理类本科393分、历史类本科439分；普通高职专科两科均为200分，必须按首选科目和批次判断。",
        "控制线不是院校专业组投档线、院校录取线、专业录取最低分或最低位次，不能单独生成录取概率。"
      ],
      "sourceFile": "data/admissions/raw/guizhou-2026/chsi-control-lines.html",
      "sourcePublishedAt": "2026-06-25"
    },
    {
      "id": "2026-guizhou-control-333b56625f9cb36cd4",
      "province": "贵州",
      "year": 2026,
      "subjectType": "历史类",
      "batch": "普通类高职（专科）录取控制分数线",
      "schoolName": "贵州省2026年高考录取控制分数线",
      "schoolTags": [
        "贵州官方内容镜像控制线",
        "普通类",
        "普通类",
        "高职（专科）"
      ],
      "city": "贵州",
      "dataType": "control-line",
      "majorName": "普通类高职（专科）录取控制分数线",
      "majorGroup": "普通类",
      "minScore": 200,
      "cultureScoreLine": 200,
      "scoreDimension": "total-score",
      "scoreBasis": "gaokao-total",
      "scoreMaximum": 750,
      "rankUnavailable": true,
      "scoreOnly": true,
      "sourceId": "official-guizhou-control-lines-2026",
      "sourceQuality": "official-content-mirror-guizhou-chsi-government-image-and-chinanews-verified",
      "sourceUrl": "https://gaokao.chsi.com.cn/gkxx/zc/ss/202606/20260625/2293847640.html",
      "formalScoreScope": "control-line-only",
      "controlLineRouteKind": "ordinary-vocational",
      "controlLineKind": "普通类高职（专科）录取控制分数线",
      "controlLineSection": "高职（专科）",
      "cautions": [
        "这是贵州省2026年普通类对应首选科目本科或高职专科录取控制分数线，只用于判断基本资格边界。",
        "物理类本科393分、历史类本科439分；普通高职专科两科均为200分，必须按首选科目和批次判断。",
        "控制线不是院校专业组投档线、院校录取线、专业录取最低分或最低位次，不能单独生成录取概率。"
      ],
      "sourceFile": "data/admissions/raw/guizhou-2026/chsi-control-lines.html",
      "sourcePublishedAt": "2026-06-25"
    },
    {
      "id": "2026-guizhou-control-6c125a3de098073228",
      "province": "贵州",
      "year": 2026,
      "subjectType": "物理类",
      "batch": "物理类特殊类型录取资格线",
      "schoolName": "贵州省2026年高考录取控制分数线",
      "schoolTags": [
        "贵州官方内容镜像控制线",
        "特殊路径",
        "特殊类型录取资格线",
        "特殊类型"
      ],
      "city": "贵州",
      "dataType": "control-line",
      "majorName": "物理类特殊类型录取资格线",
      "majorGroup": "特殊类型录取资格线",
      "minScore": 494,
      "cultureScoreLine": 494,
      "scoreDimension": "total-score",
      "scoreBasis": "gaokao-total",
      "scoreMaximum": 750,
      "rankUnavailable": true,
      "scoreOnly": true,
      "sourceId": "official-guizhou-control-lines-2026",
      "sourceQuality": "official-content-mirror-guizhou-chsi-government-image-and-chinanews-verified",
      "sourceUrl": "https://gaokao.chsi.com.cn/gkxx/zc/ss/202606/20260625/2293847640.html",
      "formalScoreScope": "special-path-only",
      "controlLineRouteKind": "special",
      "controlLineKind": "物理类特殊类型录取资格线",
      "controlLineSection": "特殊类型",
      "cautions": [
        "这是贵州省2026年特殊类型录取资格线，不替代普通类本科控制分数线。",
        "达到资格线不等于获得院校或专业录取资格，专项条件、体检政审、校测或招生章程要求须另行满足。",
        "本记录保持 special-path-only，不进入普通类院校推荐概率计算。"
      ],
      "sourceFile": "data/admissions/raw/guizhou-2026/chsi-control-lines.html",
      "sourcePublishedAt": "2026-06-25"
    },
    {
      "id": "2026-guizhou-control-7b257104192df29f03",
      "province": "贵州",
      "year": 2026,
      "subjectType": "历史类",
      "batch": "历史类特殊类型录取资格线",
      "schoolName": "贵州省2026年高考录取控制分数线",
      "schoolTags": [
        "贵州官方内容镜像控制线",
        "特殊路径",
        "特殊类型录取资格线",
        "特殊类型"
      ],
      "city": "贵州",
      "dataType": "control-line",
      "majorName": "历史类特殊类型录取资格线",
      "majorGroup": "特殊类型录取资格线",
      "minScore": 503,
      "cultureScoreLine": 503,
      "scoreDimension": "total-score",
      "scoreBasis": "gaokao-total",
      "scoreMaximum": 750,
      "rankUnavailable": true,
      "scoreOnly": true,
      "sourceId": "official-guizhou-control-lines-2026",
      "sourceQuality": "official-content-mirror-guizhou-chsi-government-image-and-chinanews-verified",
      "sourceUrl": "https://gaokao.chsi.com.cn/gkxx/zc/ss/202606/20260625/2293847640.html",
      "formalScoreScope": "special-path-only",
      "controlLineRouteKind": "special",
      "controlLineKind": "历史类特殊类型录取资格线",
      "controlLineSection": "特殊类型",
      "cautions": [
        "这是贵州省2026年特殊类型录取资格线，不替代普通类本科控制分数线。",
        "达到资格线不等于获得院校或专业录取资格，专项条件、体检政审、校测或招生章程要求须另行满足。",
        "本记录保持 special-path-only，不进入普通类院校推荐概率计算。"
      ],
      "sourceFile": "data/admissions/raw/guizhou-2026/chsi-control-lines.html",
      "sourcePublishedAt": "2026-06-25"
    },
    {
      "id": "2026-guizhou-control-05e6bf1685b1adcccd",
      "province": "贵州",
      "year": 2026,
      "subjectType": "物理类",
      "batch": "播音与主持类物理类本科文化录取控制线",
      "schoolName": "贵州省2026年高考录取控制分数线",
      "schoolTags": [
        "贵州官方内容镜像控制线",
        "特殊路径",
        "播音与主持类",
        "本科"
      ],
      "city": "贵州",
      "dataType": "control-line",
      "majorName": "播音与主持类物理类本科文化录取控制线",
      "majorGroup": "播音与主持类",
      "minScore": 334,
      "cultureScoreLine": 334,
      "professionalQualification": "专业成绩达到贵州省相应类别统考、联考或校考要求",
      "scoreDimension": "culture-and-qualification",
      "scoreBasis": "culture-score",
      "scoreMaximum": 750,
      "rankUnavailable": true,
      "scoreOnly": true,
      "sourceId": "official-guizhou-control-lines-2026",
      "sourceQuality": "official-content-mirror-guizhou-chsi-government-image-and-chinanews-verified",
      "sourceUrl": "https://gaokao.chsi.com.cn/gkxx/zc/ss/202606/20260625/2293847640.html",
      "formalScoreScope": "special-path-only",
      "controlLineRouteKind": "art",
      "controlLineKind": "播音与主持类物理类本科文化录取控制线",
      "controlLineSection": "本科",
      "cautions": [
        "这是贵州省2026年播音与主持类物理类本科文化录取控制线，只适用于对应艺体类别考生。",
        "官方控制线页面未给出本记录对应的专业统考数值；考生还必须达到相应专业成绩要求，不得把文化线当成专业线。",
        "该边界不是具体院校或专业投档线，还须核对专业合格线、综合成绩算法、招生章程和选科要求。"
      ],
      "sourceFile": "data/admissions/raw/guizhou-2026/chsi-control-lines.html",
      "sourcePublishedAt": "2026-06-25"
    },
    {
      "id": "2026-guizhou-control-c2cf0298ebc0cec905",
      "province": "贵州",
      "year": 2026,
      "subjectType": "历史类",
      "batch": "播音与主持类历史类本科文化录取控制线",
      "schoolName": "贵州省2026年高考录取控制分数线",
      "schoolTags": [
        "贵州官方内容镜像控制线",
        "特殊路径",
        "播音与主持类",
        "本科"
      ],
      "city": "贵州",
      "dataType": "control-line",
      "majorName": "播音与主持类历史类本科文化录取控制线",
      "majorGroup": "播音与主持类",
      "minScore": 373,
      "cultureScoreLine": 373,
      "professionalQualification": "专业成绩达到贵州省相应类别统考、联考或校考要求",
      "scoreDimension": "culture-and-qualification",
      "scoreBasis": "culture-score",
      "scoreMaximum": 750,
      "rankUnavailable": true,
      "scoreOnly": true,
      "sourceId": "official-guizhou-control-lines-2026",
      "sourceQuality": "official-content-mirror-guizhou-chsi-government-image-and-chinanews-verified",
      "sourceUrl": "https://gaokao.chsi.com.cn/gkxx/zc/ss/202606/20260625/2293847640.html",
      "formalScoreScope": "special-path-only",
      "controlLineRouteKind": "art",
      "controlLineKind": "播音与主持类历史类本科文化录取控制线",
      "controlLineSection": "本科",
      "cautions": [
        "这是贵州省2026年播音与主持类历史类本科文化录取控制线，只适用于对应艺体类别考生。",
        "官方控制线页面未给出本记录对应的专业统考数值；考生还必须达到相应专业成绩要求，不得把文化线当成专业线。",
        "该边界不是具体院校或专业投档线，还须核对专业合格线、综合成绩算法、招生章程和选科要求。"
      ],
      "sourceFile": "data/admissions/raw/guizhou-2026/chsi-control-lines.html",
      "sourcePublishedAt": "2026-06-25"
    },
    {
      "id": "2026-guizhou-control-0a54ee92302635852a",
      "province": "贵州",
      "year": 2026,
      "subjectType": "物理类",
      "batch": "表（导）演类（戏剧影视导演）物理类本科文化录取控制线",
      "schoolName": "贵州省2026年高考录取控制分数线",
      "schoolTags": [
        "贵州官方内容镜像控制线",
        "特殊路径",
        "表（导）演类（戏剧影视导演）",
        "本科"
      ],
      "city": "贵州",
      "dataType": "control-line",
      "majorName": "表（导）演类（戏剧影视导演）物理类本科文化录取控制线",
      "majorGroup": "表（导）演类（戏剧影视导演）",
      "minScore": 334,
      "cultureScoreLine": 334,
      "professionalQualification": "专业成绩达到贵州省相应类别统考、联考或校考要求",
      "scoreDimension": "culture-and-qualification",
      "scoreBasis": "culture-score",
      "scoreMaximum": 750,
      "rankUnavailable": true,
      "scoreOnly": true,
      "sourceId": "official-guizhou-control-lines-2026",
      "sourceQuality": "official-content-mirror-guizhou-chsi-government-image-and-chinanews-verified",
      "sourceUrl": "https://gaokao.chsi.com.cn/gkxx/zc/ss/202606/20260625/2293847640.html",
      "formalScoreScope": "special-path-only",
      "controlLineRouteKind": "art",
      "controlLineKind": "表（导）演类（戏剧影视导演）物理类本科文化录取控制线",
      "controlLineSection": "本科",
      "cautions": [
        "这是贵州省2026年表（导）演类（戏剧影视导演）物理类本科文化录取控制线，只适用于对应艺体类别考生。",
        "官方控制线页面未给出本记录对应的专业统考数值；考生还必须达到相应专业成绩要求，不得把文化线当成专业线。",
        "该边界不是具体院校或专业投档线，还须核对专业合格线、综合成绩算法、招生章程和选科要求。"
      ],
      "sourceFile": "data/admissions/raw/guizhou-2026/chsi-control-lines.html",
      "sourcePublishedAt": "2026-06-25"
    },
    {
      "id": "2026-guizhou-control-3e5cf03148c444e907",
      "province": "贵州",
      "year": 2026,
      "subjectType": "历史类",
      "batch": "表（导）演类（戏剧影视导演）历史类本科文化录取控制线",
      "schoolName": "贵州省2026年高考录取控制分数线",
      "schoolTags": [
        "贵州官方内容镜像控制线",
        "特殊路径",
        "表（导）演类（戏剧影视导演）",
        "本科"
      ],
      "city": "贵州",
      "dataType": "control-line",
      "majorName": "表（导）演类（戏剧影视导演）历史类本科文化录取控制线",
      "majorGroup": "表（导）演类（戏剧影视导演）",
      "minScore": 373,
      "cultureScoreLine": 373,
      "professionalQualification": "专业成绩达到贵州省相应类别统考、联考或校考要求",
      "scoreDimension": "culture-and-qualification",
      "scoreBasis": "culture-score",
      "scoreMaximum": 750,
      "rankUnavailable": true,
      "scoreOnly": true,
      "sourceId": "official-guizhou-control-lines-2026",
      "sourceQuality": "official-content-mirror-guizhou-chsi-government-image-and-chinanews-verified",
      "sourceUrl": "https://gaokao.chsi.com.cn/gkxx/zc/ss/202606/20260625/2293847640.html",
      "formalScoreScope": "special-path-only",
      "controlLineRouteKind": "art",
      "controlLineKind": "表（导）演类（戏剧影视导演）历史类本科文化录取控制线",
      "controlLineSection": "本科",
      "cautions": [
        "这是贵州省2026年表（导）演类（戏剧影视导演）历史类本科文化录取控制线，只适用于对应艺体类别考生。",
        "官方控制线页面未给出本记录对应的专业统考数值；考生还必须达到相应专业成绩要求，不得把文化线当成专业线。",
        "该边界不是具体院校或专业投档线，还须核对专业合格线、综合成绩算法、招生章程和选科要求。"
      ],
      "sourceFile": "data/admissions/raw/guizhou-2026/chsi-control-lines.html",
      "sourcePublishedAt": "2026-06-25"
    },
    {
      "id": "2026-guizhou-control-a917cdad08d287e8dd",
      "province": "贵州",
      "year": 2026,
      "subjectType": "物理类",
      "batch": "美术与设计类物理类本科文化录取控制线",
      "schoolName": "贵州省2026年高考录取控制分数线",
      "schoolTags": [
        "贵州官方内容镜像控制线",
        "特殊路径",
        "美术与设计类",
        "本科"
      ],
      "city": "贵州",
      "dataType": "control-line",
      "majorName": "美术与设计类物理类本科文化录取控制线",
      "majorGroup": "美术与设计类",
      "minScore": 314,
      "cultureScoreLine": 314,
      "professionalQualification": "专业成绩达到贵州省相应类别统考、联考或校考要求",
      "scoreDimension": "culture-and-qualification",
      "scoreBasis": "culture-score",
      "scoreMaximum": 750,
      "rankUnavailable": true,
      "scoreOnly": true,
      "sourceId": "official-guizhou-control-lines-2026",
      "sourceQuality": "official-content-mirror-guizhou-chsi-government-image-and-chinanews-verified",
      "sourceUrl": "https://gaokao.chsi.com.cn/gkxx/zc/ss/202606/20260625/2293847640.html",
      "formalScoreScope": "special-path-only",
      "controlLineRouteKind": "art",
      "controlLineKind": "美术与设计类物理类本科文化录取控制线",
      "controlLineSection": "本科",
      "cautions": [
        "这是贵州省2026年美术与设计类物理类本科文化录取控制线，只适用于对应艺体类别考生。",
        "官方控制线页面未给出本记录对应的专业统考数值；考生还必须达到相应专业成绩要求，不得把文化线当成专业线。",
        "该边界不是具体院校或专业投档线，还须核对专业合格线、综合成绩算法、招生章程和选科要求。"
      ],
      "sourceFile": "data/admissions/raw/guizhou-2026/chsi-control-lines.html",
      "sourcePublishedAt": "2026-06-25"
    },
    {
      "id": "2026-guizhou-control-d468de014d16ec599d",
      "province": "贵州",
      "year": 2026,
      "subjectType": "历史类",
      "batch": "美术与设计类历史类本科文化录取控制线",
      "schoolName": "贵州省2026年高考录取控制分数线",
      "schoolTags": [
        "贵州官方内容镜像控制线",
        "特殊路径",
        "美术与设计类",
        "本科"
      ],
      "city": "贵州",
      "dataType": "control-line",
      "majorName": "美术与设计类历史类本科文化录取控制线",
      "majorGroup": "美术与设计类",
      "minScore": 351,
      "cultureScoreLine": 351,
      "professionalQualification": "专业成绩达到贵州省相应类别统考、联考或校考要求",
      "scoreDimension": "culture-and-qualification",
      "scoreBasis": "culture-score",
      "scoreMaximum": 750,
      "rankUnavailable": true,
      "scoreOnly": true,
      "sourceId": "official-guizhou-control-lines-2026",
      "sourceQuality": "official-content-mirror-guizhou-chsi-government-image-and-chinanews-verified",
      "sourceUrl": "https://gaokao.chsi.com.cn/gkxx/zc/ss/202606/20260625/2293847640.html",
      "formalScoreScope": "special-path-only",
      "controlLineRouteKind": "art",
      "controlLineKind": "美术与设计类历史类本科文化录取控制线",
      "controlLineSection": "本科",
      "cautions": [
        "这是贵州省2026年美术与设计类历史类本科文化录取控制线，只适用于对应艺体类别考生。",
        "官方控制线页面未给出本记录对应的专业统考数值；考生还必须达到相应专业成绩要求，不得把文化线当成专业线。",
        "该边界不是具体院校或专业投档线，还须核对专业合格线、综合成绩算法、招生章程和选科要求。"
      ],
      "sourceFile": "data/admissions/raw/guizhou-2026/chsi-control-lines.html",
      "sourcePublishedAt": "2026-06-25"
    },
    {
      "id": "2026-guizhou-control-0d7bac97456e747460",
      "province": "贵州",
      "year": 2026,
      "subjectType": "物理类",
      "batch": "书法类物理类本科文化录取控制线",
      "schoolName": "贵州省2026年高考录取控制分数线",
      "schoolTags": [
        "贵州官方内容镜像控制线",
        "特殊路径",
        "书法类",
        "本科"
      ],
      "city": "贵州",
      "dataType": "control-line",
      "majorName": "书法类物理类本科文化录取控制线",
      "majorGroup": "书法类",
      "minScore": 314,
      "cultureScoreLine": 314,
      "professionalQualification": "专业成绩达到贵州省相应类别统考、联考或校考要求",
      "scoreDimension": "culture-and-qualification",
      "scoreBasis": "culture-score",
      "scoreMaximum": 750,
      "rankUnavailable": true,
      "scoreOnly": true,
      "sourceId": "official-guizhou-control-lines-2026",
      "sourceQuality": "official-content-mirror-guizhou-chsi-government-image-and-chinanews-verified",
      "sourceUrl": "https://gaokao.chsi.com.cn/gkxx/zc/ss/202606/20260625/2293847640.html",
      "formalScoreScope": "special-path-only",
      "controlLineRouteKind": "art",
      "controlLineKind": "书法类物理类本科文化录取控制线",
      "controlLineSection": "本科",
      "cautions": [
        "这是贵州省2026年书法类物理类本科文化录取控制线，只适用于对应艺体类别考生。",
        "官方控制线页面未给出本记录对应的专业统考数值；考生还必须达到相应专业成绩要求，不得把文化线当成专业线。",
        "该边界不是具体院校或专业投档线，还须核对专业合格线、综合成绩算法、招生章程和选科要求。"
      ],
      "sourceFile": "data/admissions/raw/guizhou-2026/chsi-control-lines.html",
      "sourcePublishedAt": "2026-06-25"
    },
    {
      "id": "2026-guizhou-control-aac1414857055b6008",
      "province": "贵州",
      "year": 2026,
      "subjectType": "历史类",
      "batch": "书法类历史类本科文化录取控制线",
      "schoolName": "贵州省2026年高考录取控制分数线",
      "schoolTags": [
        "贵州官方内容镜像控制线",
        "特殊路径",
        "书法类",
        "本科"
      ],
      "city": "贵州",
      "dataType": "control-line",
      "majorName": "书法类历史类本科文化录取控制线",
      "majorGroup": "书法类",
      "minScore": 351,
      "cultureScoreLine": 351,
      "professionalQualification": "专业成绩达到贵州省相应类别统考、联考或校考要求",
      "scoreDimension": "culture-and-qualification",
      "scoreBasis": "culture-score",
      "scoreMaximum": 750,
      "rankUnavailable": true,
      "scoreOnly": true,
      "sourceId": "official-guizhou-control-lines-2026",
      "sourceQuality": "official-content-mirror-guizhou-chsi-government-image-and-chinanews-verified",
      "sourceUrl": "https://gaokao.chsi.com.cn/gkxx/zc/ss/202606/20260625/2293847640.html",
      "formalScoreScope": "special-path-only",
      "controlLineRouteKind": "art",
      "controlLineKind": "书法类历史类本科文化录取控制线",
      "controlLineSection": "本科",
      "cautions": [
        "这是贵州省2026年书法类历史类本科文化录取控制线，只适用于对应艺体类别考生。",
        "官方控制线页面未给出本记录对应的专业统考数值；考生还必须达到相应专业成绩要求，不得把文化线当成专业线。",
        "该边界不是具体院校或专业投档线，还须核对专业合格线、综合成绩算法、招生章程和选科要求。"
      ],
      "sourceFile": "data/admissions/raw/guizhou-2026/chsi-control-lines.html",
      "sourcePublishedAt": "2026-06-25"
    },
    {
      "id": "2026-guizhou-control-d5deb17f6b6f515427",
      "province": "贵州",
      "year": 2026,
      "subjectType": "物理类",
      "batch": "音乐类物理类本科文化录取控制线",
      "schoolName": "贵州省2026年高考录取控制分数线",
      "schoolTags": [
        "贵州官方内容镜像控制线",
        "特殊路径",
        "音乐类",
        "本科"
      ],
      "city": "贵州",
      "dataType": "control-line",
      "majorName": "音乐类物理类本科文化录取控制线",
      "majorGroup": "音乐类",
      "minScore": 294,
      "cultureScoreLine": 294,
      "professionalQualification": "专业成绩达到贵州省相应类别统考、联考或校考要求",
      "scoreDimension": "culture-and-qualification",
      "scoreBasis": "culture-score",
      "scoreMaximum": 750,
      "rankUnavailable": true,
      "scoreOnly": true,
      "sourceId": "official-guizhou-control-lines-2026",
      "sourceQuality": "official-content-mirror-guizhou-chsi-government-image-and-chinanews-verified",
      "sourceUrl": "https://gaokao.chsi.com.cn/gkxx/zc/ss/202606/20260625/2293847640.html",
      "formalScoreScope": "special-path-only",
      "controlLineRouteKind": "art",
      "controlLineKind": "音乐类物理类本科文化录取控制线",
      "controlLineSection": "本科",
      "cautions": [
        "这是贵州省2026年音乐类物理类本科文化录取控制线，只适用于对应艺体类别考生。",
        "官方控制线页面未给出本记录对应的专业统考数值；考生还必须达到相应专业成绩要求，不得把文化线当成专业线。",
        "该边界不是具体院校或专业投档线，还须核对专业合格线、综合成绩算法、招生章程和选科要求。"
      ],
      "sourceFile": "data/admissions/raw/guizhou-2026/chsi-control-lines.html",
      "sourcePublishedAt": "2026-06-25"
    },
    {
      "id": "2026-guizhou-control-5ab7b420d2d5b2cc69",
      "province": "贵州",
      "year": 2026,
      "subjectType": "历史类",
      "batch": "音乐类历史类本科文化录取控制线",
      "schoolName": "贵州省2026年高考录取控制分数线",
      "schoolTags": [
        "贵州官方内容镜像控制线",
        "特殊路径",
        "音乐类",
        "本科"
      ],
      "city": "贵州",
      "dataType": "control-line",
      "majorName": "音乐类历史类本科文化录取控制线",
      "majorGroup": "音乐类",
      "minScore": 329,
      "cultureScoreLine": 329,
      "professionalQualification": "专业成绩达到贵州省相应类别统考、联考或校考要求",
      "scoreDimension": "culture-and-qualification",
      "scoreBasis": "culture-score",
      "scoreMaximum": 750,
      "rankUnavailable": true,
      "scoreOnly": true,
      "sourceId": "official-guizhou-control-lines-2026",
      "sourceQuality": "official-content-mirror-guizhou-chsi-government-image-and-chinanews-verified",
      "sourceUrl": "https://gaokao.chsi.com.cn/gkxx/zc/ss/202606/20260625/2293847640.html",
      "formalScoreScope": "special-path-only",
      "controlLineRouteKind": "art",
      "controlLineKind": "音乐类历史类本科文化录取控制线",
      "controlLineSection": "本科",
      "cautions": [
        "这是贵州省2026年音乐类历史类本科文化录取控制线，只适用于对应艺体类别考生。",
        "官方控制线页面未给出本记录对应的专业统考数值；考生还必须达到相应专业成绩要求，不得把文化线当成专业线。",
        "该边界不是具体院校或专业投档线，还须核对专业合格线、综合成绩算法、招生章程和选科要求。"
      ],
      "sourceFile": "data/admissions/raw/guizhou-2026/chsi-control-lines.html",
      "sourcePublishedAt": "2026-06-25"
    },
    {
      "id": "2026-guizhou-control-f501014d6f820fb170",
      "province": "贵州",
      "year": 2026,
      "subjectType": "物理类",
      "batch": "表（导）演类（戏剧影视表演）物理类本科文化录取控制线",
      "schoolName": "贵州省2026年高考录取控制分数线",
      "schoolTags": [
        "贵州官方内容镜像控制线",
        "特殊路径",
        "表（导）演类（戏剧影视表演）",
        "本科"
      ],
      "city": "贵州",
      "dataType": "control-line",
      "majorName": "表（导）演类（戏剧影视表演）物理类本科文化录取控制线",
      "majorGroup": "表（导）演类（戏剧影视表演）",
      "minScore": 294,
      "cultureScoreLine": 294,
      "professionalQualification": "专业成绩达到贵州省相应类别统考、联考或校考要求",
      "scoreDimension": "culture-and-qualification",
      "scoreBasis": "culture-score",
      "scoreMaximum": 750,
      "rankUnavailable": true,
      "scoreOnly": true,
      "sourceId": "official-guizhou-control-lines-2026",
      "sourceQuality": "official-content-mirror-guizhou-chsi-government-image-and-chinanews-verified",
      "sourceUrl": "https://gaokao.chsi.com.cn/gkxx/zc/ss/202606/20260625/2293847640.html",
      "formalScoreScope": "special-path-only",
      "controlLineRouteKind": "art",
      "controlLineKind": "表（导）演类（戏剧影视表演）物理类本科文化录取控制线",
      "controlLineSection": "本科",
      "cautions": [
        "这是贵州省2026年表（导）演类（戏剧影视表演）物理类本科文化录取控制线，只适用于对应艺体类别考生。",
        "官方控制线页面未给出本记录对应的专业统考数值；考生还必须达到相应专业成绩要求，不得把文化线当成专业线。",
        "该边界不是具体院校或专业投档线，还须核对专业合格线、综合成绩算法、招生章程和选科要求。"
      ],
      "sourceFile": "data/admissions/raw/guizhou-2026/chsi-control-lines.html",
      "sourcePublishedAt": "2026-06-25"
    },
    {
      "id": "2026-guizhou-control-b0bce5df2bdfdb25fb",
      "province": "贵州",
      "year": 2026,
      "subjectType": "历史类",
      "batch": "表（导）演类（戏剧影视表演）历史类本科文化录取控制线",
      "schoolName": "贵州省2026年高考录取控制分数线",
      "schoolTags": [
        "贵州官方内容镜像控制线",
        "特殊路径",
        "表（导）演类（戏剧影视表演）",
        "本科"
      ],
      "city": "贵州",
      "dataType": "control-line",
      "majorName": "表（导）演类（戏剧影视表演）历史类本科文化录取控制线",
      "majorGroup": "表（导）演类（戏剧影视表演）",
      "minScore": 329,
      "cultureScoreLine": 329,
      "professionalQualification": "专业成绩达到贵州省相应类别统考、联考或校考要求",
      "scoreDimension": "culture-and-qualification",
      "scoreBasis": "culture-score",
      "scoreMaximum": 750,
      "rankUnavailable": true,
      "scoreOnly": true,
      "sourceId": "official-guizhou-control-lines-2026",
      "sourceQuality": "official-content-mirror-guizhou-chsi-government-image-and-chinanews-verified",
      "sourceUrl": "https://gaokao.chsi.com.cn/gkxx/zc/ss/202606/20260625/2293847640.html",
      "formalScoreScope": "special-path-only",
      "controlLineRouteKind": "art",
      "controlLineKind": "表（导）演类（戏剧影视表演）历史类本科文化录取控制线",
      "controlLineSection": "本科",
      "cautions": [
        "这是贵州省2026年表（导）演类（戏剧影视表演）历史类本科文化录取控制线，只适用于对应艺体类别考生。",
        "官方控制线页面未给出本记录对应的专业统考数值；考生还必须达到相应专业成绩要求，不得把文化线当成专业线。",
        "该边界不是具体院校或专业投档线，还须核对专业合格线、综合成绩算法、招生章程和选科要求。"
      ],
      "sourceFile": "data/admissions/raw/guizhou-2026/chsi-control-lines.html",
      "sourcePublishedAt": "2026-06-25"
    },
    {
      "id": "2026-guizhou-control-c1630af2f9caf19fbe",
      "province": "贵州",
      "year": 2026,
      "subjectType": "物理类",
      "batch": "表（导）演类（服装表演）物理类本科文化录取控制线",
      "schoolName": "贵州省2026年高考录取控制分数线",
      "schoolTags": [
        "贵州官方内容镜像控制线",
        "特殊路径",
        "表（导）演类（服装表演）",
        "本科"
      ],
      "city": "贵州",
      "dataType": "control-line",
      "majorName": "表（导）演类（服装表演）物理类本科文化录取控制线",
      "majorGroup": "表（导）演类（服装表演）",
      "minScore": 294,
      "cultureScoreLine": 294,
      "professionalQualification": "专业成绩达到贵州省相应类别统考、联考或校考要求",
      "scoreDimension": "culture-and-qualification",
      "scoreBasis": "culture-score",
      "scoreMaximum": 750,
      "rankUnavailable": true,
      "scoreOnly": true,
      "sourceId": "official-guizhou-control-lines-2026",
      "sourceQuality": "official-content-mirror-guizhou-chsi-government-image-and-chinanews-verified",
      "sourceUrl": "https://gaokao.chsi.com.cn/gkxx/zc/ss/202606/20260625/2293847640.html",
      "formalScoreScope": "special-path-only",
      "controlLineRouteKind": "art",
      "controlLineKind": "表（导）演类（服装表演）物理类本科文化录取控制线",
      "controlLineSection": "本科",
      "cautions": [
        "这是贵州省2026年表（导）演类（服装表演）物理类本科文化录取控制线，只适用于对应艺体类别考生。",
        "官方控制线页面未给出本记录对应的专业统考数值；考生还必须达到相应专业成绩要求，不得把文化线当成专业线。",
        "该边界不是具体院校或专业投档线，还须核对专业合格线、综合成绩算法、招生章程和选科要求。"
      ],
      "sourceFile": "data/admissions/raw/guizhou-2026/chsi-control-lines.html",
      "sourcePublishedAt": "2026-06-25"
    },
    {
      "id": "2026-guizhou-control-3691c817b972baa135",
      "province": "贵州",
      "year": 2026,
      "subjectType": "历史类",
      "batch": "表（导）演类（服装表演）历史类本科文化录取控制线",
      "schoolName": "贵州省2026年高考录取控制分数线",
      "schoolTags": [
        "贵州官方内容镜像控制线",
        "特殊路径",
        "表（导）演类（服装表演）",
        "本科"
      ],
      "city": "贵州",
      "dataType": "control-line",
      "majorName": "表（导）演类（服装表演）历史类本科文化录取控制线",
      "majorGroup": "表（导）演类（服装表演）",
      "minScore": 329,
      "cultureScoreLine": 329,
      "professionalQualification": "专业成绩达到贵州省相应类别统考、联考或校考要求",
      "scoreDimension": "culture-and-qualification",
      "scoreBasis": "culture-score",
      "scoreMaximum": 750,
      "rankUnavailable": true,
      "scoreOnly": true,
      "sourceId": "official-guizhou-control-lines-2026",
      "sourceQuality": "official-content-mirror-guizhou-chsi-government-image-and-chinanews-verified",
      "sourceUrl": "https://gaokao.chsi.com.cn/gkxx/zc/ss/202606/20260625/2293847640.html",
      "formalScoreScope": "special-path-only",
      "controlLineRouteKind": "art",
      "controlLineKind": "表（导）演类（服装表演）历史类本科文化录取控制线",
      "controlLineSection": "本科",
      "cautions": [
        "这是贵州省2026年表（导）演类（服装表演）历史类本科文化录取控制线，只适用于对应艺体类别考生。",
        "官方控制线页面未给出本记录对应的专业统考数值；考生还必须达到相应专业成绩要求，不得把文化线当成专业线。",
        "该边界不是具体院校或专业投档线，还须核对专业合格线、综合成绩算法、招生章程和选科要求。"
      ],
      "sourceFile": "data/admissions/raw/guizhou-2026/chsi-control-lines.html",
      "sourcePublishedAt": "2026-06-25"
    },
    {
      "id": "2026-guizhou-control-a98e5fa3b1a0fc0a67",
      "province": "贵州",
      "year": 2026,
      "subjectType": "物理类",
      "batch": "舞蹈类物理类本科文化录取控制线",
      "schoolName": "贵州省2026年高考录取控制分数线",
      "schoolTags": [
        "贵州官方内容镜像控制线",
        "特殊路径",
        "舞蹈类",
        "本科"
      ],
      "city": "贵州",
      "dataType": "control-line",
      "majorName": "舞蹈类物理类本科文化录取控制线",
      "majorGroup": "舞蹈类",
      "minScore": 275,
      "cultureScoreLine": 275,
      "professionalQualification": "专业成绩达到贵州省相应类别统考、联考或校考要求",
      "scoreDimension": "culture-and-qualification",
      "scoreBasis": "culture-score",
      "scoreMaximum": 750,
      "rankUnavailable": true,
      "scoreOnly": true,
      "sourceId": "official-guizhou-control-lines-2026",
      "sourceQuality": "official-content-mirror-guizhou-chsi-government-image-and-chinanews-verified",
      "sourceUrl": "https://gaokao.chsi.com.cn/gkxx/zc/ss/202606/20260625/2293847640.html",
      "formalScoreScope": "special-path-only",
      "controlLineRouteKind": "art",
      "controlLineKind": "舞蹈类物理类本科文化录取控制线",
      "controlLineSection": "本科",
      "cautions": [
        "这是贵州省2026年舞蹈类物理类本科文化录取控制线，只适用于对应艺体类别考生。",
        "官方控制线页面未给出本记录对应的专业统考数值；考生还必须达到相应专业成绩要求，不得把文化线当成专业线。",
        "该边界不是具体院校或专业投档线，还须核对专业合格线、综合成绩算法、招生章程和选科要求。"
      ],
      "sourceFile": "data/admissions/raw/guizhou-2026/chsi-control-lines.html",
      "sourcePublishedAt": "2026-06-25"
    },
    {
      "id": "2026-guizhou-control-0672068cccb30a5570",
      "province": "贵州",
      "year": 2026,
      "subjectType": "历史类",
      "batch": "舞蹈类历史类本科文化录取控制线",
      "schoolName": "贵州省2026年高考录取控制分数线",
      "schoolTags": [
        "贵州官方内容镜像控制线",
        "特殊路径",
        "舞蹈类",
        "本科"
      ],
      "city": "贵州",
      "dataType": "control-line",
      "majorName": "舞蹈类历史类本科文化录取控制线",
      "majorGroup": "舞蹈类",
      "minScore": 307,
      "cultureScoreLine": 307,
      "professionalQualification": "专业成绩达到贵州省相应类别统考、联考或校考要求",
      "scoreDimension": "culture-and-qualification",
      "scoreBasis": "culture-score",
      "scoreMaximum": 750,
      "rankUnavailable": true,
      "scoreOnly": true,
      "sourceId": "official-guizhou-control-lines-2026",
      "sourceQuality": "official-content-mirror-guizhou-chsi-government-image-and-chinanews-verified",
      "sourceUrl": "https://gaokao.chsi.com.cn/gkxx/zc/ss/202606/20260625/2293847640.html",
      "formalScoreScope": "special-path-only",
      "controlLineRouteKind": "art",
      "controlLineKind": "舞蹈类历史类本科文化录取控制线",
      "controlLineSection": "本科",
      "cautions": [
        "这是贵州省2026年舞蹈类历史类本科文化录取控制线，只适用于对应艺体类别考生。",
        "官方控制线页面未给出本记录对应的专业统考数值；考生还必须达到相应专业成绩要求，不得把文化线当成专业线。",
        "该边界不是具体院校或专业投档线，还须核对专业合格线、综合成绩算法、招生章程和选科要求。"
      ],
      "sourceFile": "data/admissions/raw/guizhou-2026/chsi-control-lines.html",
      "sourcePublishedAt": "2026-06-25"
    },
    {
      "id": "2026-guizhou-control-40e4269a7139afdc35",
      "province": "贵州",
      "year": 2026,
      "subjectType": "物理类",
      "batch": "艺术类物理类高职（专科）文化录取控制线",
      "schoolName": "贵州省2026年高考录取控制分数线",
      "schoolTags": [
        "贵州官方内容镜像控制线",
        "特殊路径",
        "艺术类",
        "高职（专科）"
      ],
      "city": "贵州",
      "dataType": "control-line",
      "majorName": "艺术类物理类高职（专科）文化录取控制线",
      "majorGroup": "艺术类",
      "minScore": 180,
      "cultureScoreLine": 180,
      "professionalQualification": "专业成绩达到贵州省相应类别统考、联考或校考要求",
      "scoreDimension": "culture-and-qualification",
      "scoreBasis": "culture-score",
      "scoreMaximum": 750,
      "rankUnavailable": true,
      "scoreOnly": true,
      "sourceId": "official-guizhou-control-lines-2026",
      "sourceQuality": "official-content-mirror-guizhou-chsi-government-image-and-chinanews-verified",
      "sourceUrl": "https://gaokao.chsi.com.cn/gkxx/zc/ss/202606/20260625/2293847640.html",
      "formalScoreScope": "special-path-only",
      "controlLineRouteKind": "art",
      "controlLineKind": "艺术类物理类高职（专科）文化录取控制线",
      "controlLineSection": "高职（专科）",
      "cautions": [
        "这是贵州省2026年艺术类物理类高职（专科）文化录取控制线，只适用于对应艺体类别考生。",
        "官方控制线页面未给出本记录对应的专业统考数值；考生还必须达到相应专业成绩要求，不得把文化线当成专业线。",
        "该边界不是具体院校或专业投档线，还须核对专业合格线、综合成绩算法、招生章程和选科要求。"
      ],
      "sourceFile": "data/admissions/raw/guizhou-2026/chsi-control-lines.html",
      "sourcePublishedAt": "2026-06-25"
    },
    {
      "id": "2026-guizhou-control-a496c43e65491f5cf5",
      "province": "贵州",
      "year": 2026,
      "subjectType": "历史类",
      "batch": "艺术类历史类高职（专科）文化录取控制线",
      "schoolName": "贵州省2026年高考录取控制分数线",
      "schoolTags": [
        "贵州官方内容镜像控制线",
        "特殊路径",
        "艺术类",
        "高职（专科）"
      ],
      "city": "贵州",
      "dataType": "control-line",
      "majorName": "艺术类历史类高职（专科）文化录取控制线",
      "majorGroup": "艺术类",
      "minScore": 180,
      "cultureScoreLine": 180,
      "professionalQualification": "专业成绩达到贵州省相应类别统考、联考或校考要求",
      "scoreDimension": "culture-and-qualification",
      "scoreBasis": "culture-score",
      "scoreMaximum": 750,
      "rankUnavailable": true,
      "scoreOnly": true,
      "sourceId": "official-guizhou-control-lines-2026",
      "sourceQuality": "official-content-mirror-guizhou-chsi-government-image-and-chinanews-verified",
      "sourceUrl": "https://gaokao.chsi.com.cn/gkxx/zc/ss/202606/20260625/2293847640.html",
      "formalScoreScope": "special-path-only",
      "controlLineRouteKind": "art",
      "controlLineKind": "艺术类历史类高职（专科）文化录取控制线",
      "controlLineSection": "高职（专科）",
      "cautions": [
        "这是贵州省2026年艺术类历史类高职（专科）文化录取控制线，只适用于对应艺体类别考生。",
        "官方控制线页面未给出本记录对应的专业统考数值；考生还必须达到相应专业成绩要求，不得把文化线当成专业线。",
        "该边界不是具体院校或专业投档线，还须核对专业合格线、综合成绩算法、招生章程和选科要求。"
      ],
      "sourceFile": "data/admissions/raw/guizhou-2026/chsi-control-lines.html",
      "sourcePublishedAt": "2026-06-25"
    },
    {
      "id": "2026-guizhou-control-8596e15bef9e991da9",
      "province": "贵州",
      "year": 2026,
      "subjectType": "物理类",
      "batch": "体育类物理类本科文化录取控制线",
      "schoolName": "贵州省2026年高考录取控制分数线",
      "schoolTags": [
        "贵州官方内容镜像控制线",
        "特殊路径",
        "体育类",
        "本科"
      ],
      "city": "贵州",
      "dataType": "control-line",
      "majorName": "体育类物理类本科文化录取控制线",
      "majorGroup": "体育类",
      "minScore": 325,
      "cultureScoreLine": 325,
      "professionalQualification": "专业成绩达到贵州省相应类别统考、联考或校考要求",
      "scoreDimension": "culture-and-qualification",
      "scoreBasis": "culture-score",
      "scoreMaximum": 750,
      "rankUnavailable": true,
      "scoreOnly": true,
      "sourceId": "official-guizhou-control-lines-2026",
      "sourceQuality": "official-content-mirror-guizhou-chsi-government-image-and-chinanews-verified",
      "sourceUrl": "https://gaokao.chsi.com.cn/gkxx/zc/ss/202606/20260625/2293847640.html",
      "formalScoreScope": "special-path-only",
      "controlLineRouteKind": "sports",
      "controlLineKind": "体育类物理类本科文化录取控制线",
      "controlLineSection": "本科",
      "cautions": [
        "这是贵州省2026年体育类物理类本科文化录取控制线，只适用于对应艺体类别考生。",
        "官方控制线页面未给出本记录对应的专业统考数值；考生还必须达到相应专业成绩要求，不得把文化线当成专业线。",
        "该边界不是具体院校或专业投档线，还须核对专业合格线、综合成绩算法、招生章程和选科要求。"
      ],
      "sourceFile": "data/admissions/raw/guizhou-2026/chsi-control-lines.html",
      "sourcePublishedAt": "2026-06-25"
    },
    {
      "id": "2026-guizhou-control-05fc54e5c9cd3da42e",
      "province": "贵州",
      "year": 2026,
      "subjectType": "历史类",
      "batch": "体育类历史类本科文化录取控制线",
      "schoolName": "贵州省2026年高考录取控制分数线",
      "schoolTags": [
        "贵州官方内容镜像控制线",
        "特殊路径",
        "体育类",
        "本科"
      ],
      "city": "贵州",
      "dataType": "control-line",
      "majorName": "体育类历史类本科文化录取控制线",
      "majorGroup": "体育类",
      "minScore": 351,
      "cultureScoreLine": 351,
      "professionalQualification": "专业成绩达到贵州省相应类别统考、联考或校考要求",
      "scoreDimension": "culture-and-qualification",
      "scoreBasis": "culture-score",
      "scoreMaximum": 750,
      "rankUnavailable": true,
      "scoreOnly": true,
      "sourceId": "official-guizhou-control-lines-2026",
      "sourceQuality": "official-content-mirror-guizhou-chsi-government-image-and-chinanews-verified",
      "sourceUrl": "https://gaokao.chsi.com.cn/gkxx/zc/ss/202606/20260625/2293847640.html",
      "formalScoreScope": "special-path-only",
      "controlLineRouteKind": "sports",
      "controlLineKind": "体育类历史类本科文化录取控制线",
      "controlLineSection": "本科",
      "cautions": [
        "这是贵州省2026年体育类历史类本科文化录取控制线，只适用于对应艺体类别考生。",
        "官方控制线页面未给出本记录对应的专业统考数值；考生还必须达到相应专业成绩要求，不得把文化线当成专业线。",
        "该边界不是具体院校或专业投档线，还须核对专业合格线、综合成绩算法、招生章程和选科要求。"
      ],
      "sourceFile": "data/admissions/raw/guizhou-2026/chsi-control-lines.html",
      "sourcePublishedAt": "2026-06-25"
    },
    {
      "id": "2026-guizhou-control-62461f1478243aa3b8",
      "province": "贵州",
      "year": 2026,
      "subjectType": "物理类",
      "batch": "体育类物理类高职（专科）文化录取控制线",
      "schoolName": "贵州省2026年高考录取控制分数线",
      "schoolTags": [
        "贵州官方内容镜像控制线",
        "特殊路径",
        "体育类",
        "高职（专科）"
      ],
      "city": "贵州",
      "dataType": "control-line",
      "majorName": "体育类物理类高职（专科）文化录取控制线",
      "majorGroup": "体育类",
      "minScore": 180,
      "cultureScoreLine": 180,
      "professionalQualification": "专业成绩达到贵州省相应类别统考、联考或校考要求",
      "scoreDimension": "culture-and-qualification",
      "scoreBasis": "culture-score",
      "scoreMaximum": 750,
      "rankUnavailable": true,
      "scoreOnly": true,
      "sourceId": "official-guizhou-control-lines-2026",
      "sourceQuality": "official-content-mirror-guizhou-chsi-government-image-and-chinanews-verified",
      "sourceUrl": "https://gaokao.chsi.com.cn/gkxx/zc/ss/202606/20260625/2293847640.html",
      "formalScoreScope": "special-path-only",
      "controlLineRouteKind": "sports",
      "controlLineKind": "体育类物理类高职（专科）文化录取控制线",
      "controlLineSection": "高职（专科）",
      "cautions": [
        "这是贵州省2026年体育类物理类高职（专科）文化录取控制线，只适用于对应艺体类别考生。",
        "官方控制线页面未给出本记录对应的专业统考数值；考生还必须达到相应专业成绩要求，不得把文化线当成专业线。",
        "该边界不是具体院校或专业投档线，还须核对专业合格线、综合成绩算法、招生章程和选科要求。"
      ],
      "sourceFile": "data/admissions/raw/guizhou-2026/chsi-control-lines.html",
      "sourcePublishedAt": "2026-06-25"
    },
    {
      "id": "2026-guizhou-control-95c8023fac1af74e7c",
      "province": "贵州",
      "year": 2026,
      "subjectType": "历史类",
      "batch": "体育类历史类高职（专科）文化录取控制线",
      "schoolName": "贵州省2026年高考录取控制分数线",
      "schoolTags": [
        "贵州官方内容镜像控制线",
        "特殊路径",
        "体育类",
        "高职（专科）"
      ],
      "city": "贵州",
      "dataType": "control-line",
      "majorName": "体育类历史类高职（专科）文化录取控制线",
      "majorGroup": "体育类",
      "minScore": 180,
      "cultureScoreLine": 180,
      "professionalQualification": "专业成绩达到贵州省相应类别统考、联考或校考要求",
      "scoreDimension": "culture-and-qualification",
      "scoreBasis": "culture-score",
      "scoreMaximum": 750,
      "rankUnavailable": true,
      "scoreOnly": true,
      "sourceId": "official-guizhou-control-lines-2026",
      "sourceQuality": "official-content-mirror-guizhou-chsi-government-image-and-chinanews-verified",
      "sourceUrl": "https://gaokao.chsi.com.cn/gkxx/zc/ss/202606/20260625/2293847640.html",
      "formalScoreScope": "special-path-only",
      "controlLineRouteKind": "sports",
      "controlLineKind": "体育类历史类高职（专科）文化录取控制线",
      "controlLineSection": "高职（专科）",
      "cautions": [
        "这是贵州省2026年体育类历史类高职（专科）文化录取控制线，只适用于对应艺体类别考生。",
        "官方控制线页面未给出本记录对应的专业统考数值；考生还必须达到相应专业成绩要求，不得把文化线当成专业线。",
        "该边界不是具体院校或专业投档线，还须核对专业合格线、综合成绩算法、招生章程和选科要求。"
      ],
      "sourceFile": "data/admissions/raw/guizhou-2026/chsi-control-lines.html",
      "sourcePublishedAt": "2026-06-25"
    },
    {
      "id": "2026-guizhou-control-7bfac1a32b6065a99f",
      "province": "贵州",
      "year": 2026,
      "subjectType": "民汉双语",
      "batch": "民汉双语专业民族语言口语测试成绩资格线",
      "schoolName": "贵州省2026年高考录取控制分数线",
      "schoolTags": [
        "贵州官方内容镜像控制线",
        "特殊路径",
        "民汉双语专业",
        "口语测试"
      ],
      "city": "贵州",
      "dataType": "control-line",
      "majorName": "民汉双语专业民族语言口语测试成绩资格线",
      "majorGroup": "民汉双语专业",
      "candidateCategory": "民汉双语专业",
      "minScore": 97.7,
      "scoreDimension": "oral-test-score",
      "scoreBasis": "minority-language-oral-test",
      "scoreMaximum": 100,
      "rankUnavailable": true,
      "scoreOnly": true,
      "sourceId": "official-guizhou-control-lines-2026",
      "sourceQuality": "official-content-mirror-guizhou-chsi-government-image-and-chinanews-verified",
      "sourceUrl": "https://gaokao.chsi.com.cn/gkxx/zc/ss/202606/20260625/2293847640.html",
      "formalScoreScope": "special-path-only",
      "controlLineRouteKind": "minority-language-oral",
      "controlLineKind": "民汉双语专业民族语言口语测试成绩资格线",
      "controlLineSection": "口语测试",
      "cautions": [
        "这是贵州省2026年民汉双语专业民族语言口语测试成绩资格线，只适用于具备相应报考资格的考生。",
        "97.70分是民族语言口语测试口径，不是750分制普通高考总分，不能进入普通物理类或历史类资格路由。",
        "达到口语资格线不等于获得院校或专业录取资格，仍须满足文化成绩、招生计划和其他报考条件。"
      ],
      "sourceFile": "data/admissions/raw/guizhou-2026/chsi-control-lines.html",
      "sourcePublishedAt": "2026-06-25"
    }
  ],
  "diagnostics": {
    "recordCount": 29,
    "ordinaryRecords": 4,
    "specialPathRecords": 25,
    "artSportsCultureRecords": 22,
    "professionalNumericRecords": 0,
    "routeCounts": {
      "ordinary-bachelor": 2,
      "ordinary-vocational": 2,
      "special": 2,
      "art": 18,
      "sports": 4,
      "minority-language-oral": 1
    },
    "ordinaryBoundaries": {
      "historyBachelor": 439,
      "historyVocational": 200,
      "physicsBachelor": 393,
      "physicsVocational": 200
    },
    "rankRecords": 1201,
    "rankValueChanges": 0,
    "scoreMaximum": 750
  }
}
