{
  "dataset": "official-fujian-control-lines-2026-import",
  "generatedAt": "2026-07-16T00:45:00.000Z",
  "scope": {
    "province": "福建",
    "year": 2026,
    "sourceKind": "official-control-lines"
  },
  "notes": [
    "官方正文以图片发布；本导入器锁定正文和原图字节数及SHA-256，再按原图逐项结构化。",
    "普通类本科/高职（专科）4条只作资格路由；特殊类型、艺术、体育18条保持特殊路径隔离。",
    "艺术和体育文化课、专业课门槛分字段保存；戏曲省际联考与其他艺术省统考分开。"
  ],
  "sourceNotes": [
    {
      "id": "official-fujian-control-lines-2026",
      "province": "福建",
      "title": "福建省2026年普通高考录取控制分数线公布",
      "publisher": "福建省教育考试院",
      "publishedAt": "2026-06-24 16:32",
      "url": "https://www.eeafj.cn/gkptgkgsgg/20260624/14697.html",
      "attachmentUrls": [
        "https://www.eeafj.cn/u/cms/default/202606/20260624151636_4.jpg"
      ],
      "relatedUrls": [
        "https://www.eeafj.cn/gkptgkgsgg/20260625/14698.html",
        "https://www.eeafj.cn/gkptgkgsgg/20260625/14699.html"
      ],
      "quality": "official-fujian-control-line-image-verified",
      "usage": "抽取福建2026普通类、特殊类型、艺术类和体育类控制线22条；仅普通物理/历史本科与高职（专科）4条参与普通资格路由。",
      "parsedRecords": 22,
      "controlPageBytes": 16211,
      "controlPageSha256": "c2acd98f9bd57a7031fb3e28de51849d5f2427b5535108abc418e22c71391a3b",
      "controlImageBytes": 1297816,
      "controlImageSha256": "3e02438605e2703d2a86be08eec2fddfa797e2b313c8795a2082e9418245e645",
      "rankPageEvidence": [
        {
          "subjectType": "历史类",
          "url": "https://www.eeafj.cn/gkptgkgsgg/20260625/14698.html",
          "bytes": 16105,
          "sha256": "87831249b32f866217c490fde278319be38e2b4e400a9a20b000b12d7000e7e5"
        },
        {
          "subjectType": "物理类",
          "url": "https://www.eeafj.cn/gkptgkgsgg/20260625/14699.html",
          "bytes": 16107,
          "sha256": "340b729d2a28e7e9eb648b0989869a56dd7c9170c7c64321fd0bdf1b35507107"
        }
      ],
      "rankImageEvidence": [
        {
          "subjectType": "历史类",
          "pageNumber": 1,
          "url": "https://www.eeafj.cn/u/cms/default/202606/20260625091641_469.jpg",
          "bytes": 941643,
          "sha256": "cd3171a0d1a20d917bd07ec76128f719ab20caccfcaceb604ad3810e8a8681e9"
        },
        {
          "subjectType": "历史类",
          "pageNumber": 2,
          "url": "https://www.eeafj.cn/u/cms/default/202606/20260625091642_980.jpg",
          "bytes": 1027070,
          "sha256": "b5d097cf46da309e4e531a136f1f64927e7d7a28b73c59ebe0341f48f9085a89"
        },
        {
          "subjectType": "历史类",
          "pageNumber": 3,
          "url": "https://www.eeafj.cn/u/cms/default/202606/20260625091642_682.jpg",
          "bytes": 1014994,
          "sha256": "2b04287960e3a18a8f132a0aa306ab127ce9f6016b4a9304697a4a149464258c"
        },
        {
          "subjectType": "历史类",
          "pageNumber": 4,
          "url": "https://www.eeafj.cn/u/cms/default/202606/20260625091642_527.jpg",
          "bytes": 907839,
          "sha256": "ab7ad78fa4d94fa8843c38b9f0741633c444a8e55a0af985476ca6744c14564e"
        },
        {
          "subjectType": "物理类",
          "pageNumber": 1,
          "url": "https://www.eeafj.cn/u/cms/default/202606/20260625091744_154.jpg",
          "bytes": 973201,
          "sha256": "7d1a23683ef5f3358f0dc56db5ab9259df14652b8513481af9d19b5176cc2e25"
        },
        {
          "subjectType": "物理类",
          "pageNumber": 2,
          "url": "https://www.eeafj.cn/u/cms/default/202606/20260625091744_318.jpg",
          "bytes": 1013594,
          "sha256": "b5ad7c44e2c3ea41c5bbd73e0b43e643fbb89f6200a6cfce019fd070974ee632"
        },
        {
          "subjectType": "物理类",
          "pageNumber": 3,
          "url": "https://www.eeafj.cn/u/cms/default/202606/20260625091744_501.jpg",
          "bytes": 1006062,
          "sha256": "f3bd3bdd42c2d24cd92b330f32ecbf090826019a7cb8a90271d948b31c17afa0"
        },
        {
          "subjectType": "物理类",
          "pageNumber": 4,
          "url": "https://www.eeafj.cn/u/cms/default/202606/20260625091744_834.jpg",
          "bytes": 993690,
          "sha256": "75e3778bc018329a92f8e34a530bc4d10ec7ce1ae68ec436beef2218cc92594a"
        }
      ],
      "evidenceBoundary": "control-line-only=4; special-path-only=18; culture-plus-professional=16; not institution-group, institution or major admission score"
    }
  ],
  "records": [
    {
      "id": "2026-fujian-control-41e0c4ffbd12b35006",
      "province": "福建",
      "year": 2026,
      "subjectType": "物理类",
      "batch": "普通类本科录取控制分数线",
      "schoolName": "福建省2026年普通高考录取控制分数线公布",
      "schoolTags": [
        "福建官方控制线",
        "普通类",
        "普通类",
        "本科"
      ],
      "city": "福建",
      "dataType": "control-line",
      "majorName": "普通类本科录取控制分数线",
      "majorGroup": "普通类",
      "minScore": 446,
      "cultureScoreLine": 446,
      "scoreDimension": "culture-score",
      "scoreBasis": "gaokao-total",
      "rankUnavailable": true,
      "scoreOnly": true,
      "sourceId": "official-fujian-control-lines-2026",
      "sourceQuality": "official-fujian-control-line-image-verified",
      "sourceUrl": "https://www.eeafj.cn/gkptgkgsgg/20260624/14697.html",
      "formalScoreScope": "control-line-only",
      "controlLineRouteKind": "ordinary-bachelor",
      "controlLineKind": "普通类录取控制分数线",
      "controlLineSection": "本科",
      "cautions": [
        "这是福建省2026年普通类本科或高职（专科）录取控制分数线，只用于对应首选科目的普通批资格边界。",
        "达到控制线不等于达到任何具体院校专业组、院校或专业的实际投档录取线。",
        "历史类和物理类不得混用；特殊类型、艺术类和体育类控制线不参与普通类推荐路由。"
      ],
      "sourceFile": "data/admissions/raw/official-fujian-control-lines-2026/control-lines.jpg",
      "sourcePublishedAt": "2026-06-24"
    },
    {
      "id": "2026-fujian-control-62b43e54a1d345d0af",
      "province": "福建",
      "year": 2026,
      "subjectType": "物理类",
      "batch": "普通类高职（专科）录取控制分数线",
      "schoolName": "福建省2026年普通高考录取控制分数线公布",
      "schoolTags": [
        "福建官方控制线",
        "普通类",
        "普通类",
        "高职（专科）"
      ],
      "city": "福建",
      "dataType": "control-line",
      "majorName": "普通类高职（专科）录取控制分数线",
      "majorGroup": "普通类",
      "minScore": 235,
      "cultureScoreLine": 235,
      "scoreDimension": "culture-score",
      "scoreBasis": "gaokao-total",
      "rankUnavailable": true,
      "scoreOnly": true,
      "sourceId": "official-fujian-control-lines-2026",
      "sourceQuality": "official-fujian-control-line-image-verified",
      "sourceUrl": "https://www.eeafj.cn/gkptgkgsgg/20260624/14697.html",
      "formalScoreScope": "control-line-only",
      "controlLineRouteKind": "ordinary-vocational",
      "controlLineKind": "普通类录取控制分数线",
      "controlLineSection": "高职（专科）",
      "cautions": [
        "这是福建省2026年普通类本科或高职（专科）录取控制分数线，只用于对应首选科目的普通批资格边界。",
        "达到控制线不等于达到任何具体院校专业组、院校或专业的实际投档录取线。",
        "历史类和物理类不得混用；特殊类型、艺术类和体育类控制线不参与普通类推荐路由。"
      ],
      "sourceFile": "data/admissions/raw/official-fujian-control-lines-2026/control-lines.jpg",
      "sourcePublishedAt": "2026-06-24"
    },
    {
      "id": "2026-fujian-control-46db6a9cb301cd228b",
      "province": "福建",
      "year": 2026,
      "subjectType": "物理类",
      "batch": "特殊类型招生特殊类型录取控制分数线",
      "schoolName": "福建省2026年普通高考录取控制分数线公布",
      "schoolTags": [
        "福建官方控制线",
        "特殊路径",
        "特殊类型招生",
        "特殊类型"
      ],
      "city": "福建",
      "dataType": "control-line",
      "majorName": "特殊类型招生特殊类型录取控制分数线",
      "majorGroup": "特殊类型招生",
      "minScore": 528,
      "cultureScoreLine": 528,
      "scoreDimension": "culture-score",
      "scoreBasis": "gaokao-total",
      "rankUnavailable": true,
      "scoreOnly": true,
      "sourceId": "official-fujian-control-lines-2026",
      "sourceQuality": "official-fujian-control-line-image-verified",
      "sourceUrl": "https://www.eeafj.cn/gkptgkgsgg/20260624/14697.html",
      "formalScoreScope": "special-path-only",
      "controlLineRouteKind": "special",
      "controlLineKind": "特殊类型招生录取控制分数线",
      "controlLineSection": "特殊类型",
      "cautions": [
        "这是福建省2026年特殊类型、艺术类或体育类控制线，不适用于普通类考生直接推荐。",
        "该分数只适用于对应特殊类型招生路径。",
        "控制线不是具体院校专业组、院校或专业的实际投档录取线。"
      ],
      "sourceFile": "data/admissions/raw/official-fujian-control-lines-2026/control-lines.jpg",
      "sourcePublishedAt": "2026-06-24"
    },
    {
      "id": "2026-fujian-control-63424b4612a4c48c86",
      "province": "福建",
      "year": 2026,
      "subjectType": "历史类",
      "batch": "普通类本科录取控制分数线",
      "schoolName": "福建省2026年普通高考录取控制分数线公布",
      "schoolTags": [
        "福建官方控制线",
        "普通类",
        "普通类",
        "本科"
      ],
      "city": "福建",
      "dataType": "control-line",
      "majorName": "普通类本科录取控制分数线",
      "majorGroup": "普通类",
      "minScore": 458,
      "cultureScoreLine": 458,
      "scoreDimension": "culture-score",
      "scoreBasis": "gaokao-total",
      "rankUnavailable": true,
      "scoreOnly": true,
      "sourceId": "official-fujian-control-lines-2026",
      "sourceQuality": "official-fujian-control-line-image-verified",
      "sourceUrl": "https://www.eeafj.cn/gkptgkgsgg/20260624/14697.html",
      "formalScoreScope": "control-line-only",
      "controlLineRouteKind": "ordinary-bachelor",
      "controlLineKind": "普通类录取控制分数线",
      "controlLineSection": "本科",
      "cautions": [
        "这是福建省2026年普通类本科或高职（专科）录取控制分数线，只用于对应首选科目的普通批资格边界。",
        "达到控制线不等于达到任何具体院校专业组、院校或专业的实际投档录取线。",
        "历史类和物理类不得混用；特殊类型、艺术类和体育类控制线不参与普通类推荐路由。"
      ],
      "sourceFile": "data/admissions/raw/official-fujian-control-lines-2026/control-lines.jpg",
      "sourcePublishedAt": "2026-06-24"
    },
    {
      "id": "2026-fujian-control-1ce32e7e9c35e236fa",
      "province": "福建",
      "year": 2026,
      "subjectType": "历史类",
      "batch": "普通类高职（专科）录取控制分数线",
      "schoolName": "福建省2026年普通高考录取控制分数线公布",
      "schoolTags": [
        "福建官方控制线",
        "普通类",
        "普通类",
        "高职（专科）"
      ],
      "city": "福建",
      "dataType": "control-line",
      "majorName": "普通类高职（专科）录取控制分数线",
      "majorGroup": "普通类",
      "minScore": 235,
      "cultureScoreLine": 235,
      "scoreDimension": "culture-score",
      "scoreBasis": "gaokao-total",
      "rankUnavailable": true,
      "scoreOnly": true,
      "sourceId": "official-fujian-control-lines-2026",
      "sourceQuality": "official-fujian-control-line-image-verified",
      "sourceUrl": "https://www.eeafj.cn/gkptgkgsgg/20260624/14697.html",
      "formalScoreScope": "control-line-only",
      "controlLineRouteKind": "ordinary-vocational",
      "controlLineKind": "普通类录取控制分数线",
      "controlLineSection": "高职（专科）",
      "cautions": [
        "这是福建省2026年普通类本科或高职（专科）录取控制分数线，只用于对应首选科目的普通批资格边界。",
        "达到控制线不等于达到任何具体院校专业组、院校或专业的实际投档录取线。",
        "历史类和物理类不得混用；特殊类型、艺术类和体育类控制线不参与普通类推荐路由。"
      ],
      "sourceFile": "data/admissions/raw/official-fujian-control-lines-2026/control-lines.jpg",
      "sourcePublishedAt": "2026-06-24"
    },
    {
      "id": "2026-fujian-control-46ebd0c5e1e32a7612",
      "province": "福建",
      "year": 2026,
      "subjectType": "历史类",
      "batch": "特殊类型招生特殊类型录取控制分数线",
      "schoolName": "福建省2026年普通高考录取控制分数线公布",
      "schoolTags": [
        "福建官方控制线",
        "特殊路径",
        "特殊类型招生",
        "特殊类型"
      ],
      "city": "福建",
      "dataType": "control-line",
      "majorName": "特殊类型招生特殊类型录取控制分数线",
      "majorGroup": "特殊类型招生",
      "minScore": 533,
      "cultureScoreLine": 533,
      "scoreDimension": "culture-score",
      "scoreBasis": "gaokao-total",
      "rankUnavailable": true,
      "scoreOnly": true,
      "sourceId": "official-fujian-control-lines-2026",
      "sourceQuality": "official-fujian-control-line-image-verified",
      "sourceUrl": "https://www.eeafj.cn/gkptgkgsgg/20260624/14697.html",
      "formalScoreScope": "special-path-only",
      "controlLineRouteKind": "special",
      "controlLineKind": "特殊类型招生录取控制分数线",
      "controlLineSection": "特殊类型",
      "cautions": [
        "这是福建省2026年特殊类型、艺术类或体育类控制线，不适用于普通类考生直接推荐。",
        "该分数只适用于对应特殊类型招生路径。",
        "控制线不是具体院校专业组、院校或专业的实际投档录取线。"
      ],
      "sourceFile": "data/admissions/raw/official-fujian-control-lines-2026/control-lines.jpg",
      "sourcePublishedAt": "2026-06-24"
    },
    {
      "id": "2026-fujian-control-c29d40c5ed562795a6",
      "province": "福建",
      "year": 2026,
      "subjectType": "艺术类（物理科目组）",
      "batch": "音乐教育类、戏剧影视导演类、播音与主持类、美术与设计类、书法类本科录取控制分数线",
      "schoolName": "福建省2026年普通高考录取控制分数线公布",
      "schoolTags": [
        "福建官方控制线",
        "特殊路径",
        "音乐教育类、戏剧影视导演类、播音与主持类、美术与设计类、书法类",
        "本科"
      ],
      "city": "福建",
      "dataType": "control-line",
      "majorName": "音乐教育类、戏剧影视导演类、播音与主持类、美术与设计类、书法类本科录取控制分数线",
      "majorGroup": "音乐教育类、戏剧影视导演类、播音与主持类、美术与设计类、书法类",
      "minScore": 335,
      "cultureScoreLine": 335,
      "scoreDimension": "culture-score",
      "scoreBasis": "gaokao-total",
      "professionalMinScore": 195,
      "professionalScoreMetric": "professional-unified-exam",
      "rankUnavailable": true,
      "scoreOnly": true,
      "sourceId": "official-fujian-control-lines-2026",
      "sourceQuality": "official-fujian-control-line-image-verified",
      "sourceUrl": "https://www.eeafj.cn/gkptgkgsgg/20260624/14697.html",
      "formalScoreScope": "special-path-only",
      "controlLineRouteKind": "art",
      "controlLineKind": "音乐教育类、戏剧影视导演类、播音与主持类、美术与设计类、书法类录取控制分数线",
      "controlLineSection": "本科",
      "cautions": [
        "这是福建省2026年特殊类型、艺术类或体育类控制线，不适用于普通类考生直接推荐。",
        "文化课分与专业统考或省际联考分是两个必须分别达到的门槛，不得相加或互相替代。",
        "控制线不是具体院校专业组、院校或专业的实际投档录取线。"
      ],
      "sourceFile": "data/admissions/raw/official-fujian-control-lines-2026/control-lines.jpg",
      "sourcePublishedAt": "2026-06-24"
    },
    {
      "id": "2026-fujian-control-ed7e44c3223d8e2ce1",
      "province": "福建",
      "year": 2026,
      "subjectType": "艺术类（物理科目组）",
      "batch": "音乐教育类、戏剧影视导演类、播音与主持类、美术与设计类、书法类高职（专科）录取控制分数线",
      "schoolName": "福建省2026年普通高考录取控制分数线公布",
      "schoolTags": [
        "福建官方控制线",
        "特殊路径",
        "音乐教育类、戏剧影视导演类、播音与主持类、美术与设计类、书法类",
        "高职（专科）"
      ],
      "city": "福建",
      "dataType": "control-line",
      "majorName": "音乐教育类、戏剧影视导演类、播音与主持类、美术与设计类、书法类高职（专科）录取控制分数线",
      "majorGroup": "音乐教育类、戏剧影视导演类、播音与主持类、美术与设计类、书法类",
      "minScore": 165,
      "cultureScoreLine": 165,
      "scoreDimension": "culture-score",
      "scoreBasis": "gaokao-total",
      "professionalMinScore": 180,
      "professionalScoreMetric": "professional-unified-exam",
      "rankUnavailable": true,
      "scoreOnly": true,
      "sourceId": "official-fujian-control-lines-2026",
      "sourceQuality": "official-fujian-control-line-image-verified",
      "sourceUrl": "https://www.eeafj.cn/gkptgkgsgg/20260624/14697.html",
      "formalScoreScope": "special-path-only",
      "controlLineRouteKind": "art",
      "controlLineKind": "音乐教育类、戏剧影视导演类、播音与主持类、美术与设计类、书法类录取控制分数线",
      "controlLineSection": "高职（专科）",
      "cautions": [
        "这是福建省2026年特殊类型、艺术类或体育类控制线，不适用于普通类考生直接推荐。",
        "文化课分与专业统考或省际联考分是两个必须分别达到的门槛，不得相加或互相替代。",
        "控制线不是具体院校专业组、院校或专业的实际投档录取线。"
      ],
      "sourceFile": "data/admissions/raw/official-fujian-control-lines-2026/control-lines.jpg",
      "sourcePublishedAt": "2026-06-24"
    },
    {
      "id": "2026-fujian-control-a1b878202c49f257f3",
      "province": "福建",
      "year": 2026,
      "subjectType": "艺术类（物理科目组）",
      "batch": "音乐表演类、戏剧影视表演类、服装表演类、舞蹈类本科录取控制分数线",
      "schoolName": "福建省2026年普通高考录取控制分数线公布",
      "schoolTags": [
        "福建官方控制线",
        "特殊路径",
        "音乐表演类、戏剧影视表演类、服装表演类、舞蹈类",
        "本科"
      ],
      "city": "福建",
      "dataType": "control-line",
      "majorName": "音乐表演类、戏剧影视表演类、服装表演类、舞蹈类本科录取控制分数线",
      "majorGroup": "音乐表演类、戏剧影视表演类、服装表演类、舞蹈类",
      "minScore": 312,
      "cultureScoreLine": 312,
      "scoreDimension": "culture-score",
      "scoreBasis": "gaokao-total",
      "professionalMinScore": 195,
      "professionalScoreMetric": "professional-unified-exam",
      "rankUnavailable": true,
      "scoreOnly": true,
      "sourceId": "official-fujian-control-lines-2026",
      "sourceQuality": "official-fujian-control-line-image-verified",
      "sourceUrl": "https://www.eeafj.cn/gkptgkgsgg/20260624/14697.html",
      "formalScoreScope": "special-path-only",
      "controlLineRouteKind": "art",
      "controlLineKind": "音乐表演类、戏剧影视表演类、服装表演类、舞蹈类录取控制分数线",
      "controlLineSection": "本科",
      "cautions": [
        "这是福建省2026年特殊类型、艺术类或体育类控制线，不适用于普通类考生直接推荐。",
        "文化课分与专业统考或省际联考分是两个必须分别达到的门槛，不得相加或互相替代。",
        "控制线不是具体院校专业组、院校或专业的实际投档录取线。"
      ],
      "sourceFile": "data/admissions/raw/official-fujian-control-lines-2026/control-lines.jpg",
      "sourcePublishedAt": "2026-06-24"
    },
    {
      "id": "2026-fujian-control-365eee4996949506ce",
      "province": "福建",
      "year": 2026,
      "subjectType": "艺术类（物理科目组）",
      "batch": "音乐表演类、戏剧影视表演类、服装表演类、舞蹈类高职（专科）录取控制分数线",
      "schoolName": "福建省2026年普通高考录取控制分数线公布",
      "schoolTags": [
        "福建官方控制线",
        "特殊路径",
        "音乐表演类、戏剧影视表演类、服装表演类、舞蹈类",
        "高职（专科）"
      ],
      "city": "福建",
      "dataType": "control-line",
      "majorName": "音乐表演类、戏剧影视表演类、服装表演类、舞蹈类高职（专科）录取控制分数线",
      "majorGroup": "音乐表演类、戏剧影视表演类、服装表演类、舞蹈类",
      "minScore": 165,
      "cultureScoreLine": 165,
      "scoreDimension": "culture-score",
      "scoreBasis": "gaokao-total",
      "professionalMinScore": 180,
      "professionalScoreMetric": "professional-unified-exam",
      "rankUnavailable": true,
      "scoreOnly": true,
      "sourceId": "official-fujian-control-lines-2026",
      "sourceQuality": "official-fujian-control-line-image-verified",
      "sourceUrl": "https://www.eeafj.cn/gkptgkgsgg/20260624/14697.html",
      "formalScoreScope": "special-path-only",
      "controlLineRouteKind": "art",
      "controlLineKind": "音乐表演类、戏剧影视表演类、服装表演类、舞蹈类录取控制分数线",
      "controlLineSection": "高职（专科）",
      "cautions": [
        "这是福建省2026年特殊类型、艺术类或体育类控制线，不适用于普通类考生直接推荐。",
        "文化课分与专业统考或省际联考分是两个必须分别达到的门槛，不得相加或互相替代。",
        "控制线不是具体院校专业组、院校或专业的实际投档录取线。"
      ],
      "sourceFile": "data/admissions/raw/official-fujian-control-lines-2026/control-lines.jpg",
      "sourcePublishedAt": "2026-06-24"
    },
    {
      "id": "2026-fujian-control-e137d560b64ca54d31",
      "province": "福建",
      "year": 2026,
      "subjectType": "艺术类（物理科目组）",
      "batch": "戏曲类本科录取控制分数线",
      "schoolName": "福建省2026年普通高考录取控制分数线公布",
      "schoolTags": [
        "福建官方控制线",
        "特殊路径",
        "戏曲类",
        "本科"
      ],
      "city": "福建",
      "dataType": "control-line",
      "majorName": "戏曲类本科录取控制分数线",
      "majorGroup": "戏曲类",
      "minScore": 312,
      "cultureScoreLine": 312,
      "scoreDimension": "culture-score",
      "scoreBasis": "gaokao-total",
      "professionalMinScore": 180,
      "professionalScoreMetric": "xiqu-interprovincial-joint-exam",
      "rankUnavailable": true,
      "scoreOnly": true,
      "sourceId": "official-fujian-control-lines-2026",
      "sourceQuality": "official-fujian-control-line-image-verified",
      "sourceUrl": "https://www.eeafj.cn/gkptgkgsgg/20260624/14697.html",
      "formalScoreScope": "special-path-only",
      "controlLineRouteKind": "art",
      "controlLineKind": "戏曲类录取控制分数线",
      "controlLineSection": "本科",
      "cautions": [
        "这是福建省2026年特殊类型、艺术类或体育类控制线，不适用于普通类考生直接推荐。",
        "文化课分与专业统考或省际联考分是两个必须分别达到的门槛，不得相加或互相替代。",
        "控制线不是具体院校专业组、院校或专业的实际投档录取线。"
      ],
      "sourceFile": "data/admissions/raw/official-fujian-control-lines-2026/control-lines.jpg",
      "sourcePublishedAt": "2026-06-24"
    },
    {
      "id": "2026-fujian-control-417d073c72ef08c4cf",
      "province": "福建",
      "year": 2026,
      "subjectType": "艺术类（物理科目组）",
      "batch": "戏曲类高职（专科）录取控制分数线",
      "schoolName": "福建省2026年普通高考录取控制分数线公布",
      "schoolTags": [
        "福建官方控制线",
        "特殊路径",
        "戏曲类",
        "高职（专科）"
      ],
      "city": "福建",
      "dataType": "control-line",
      "majorName": "戏曲类高职（专科）录取控制分数线",
      "majorGroup": "戏曲类",
      "minScore": 165,
      "cultureScoreLine": 165,
      "scoreDimension": "culture-score",
      "scoreBasis": "gaokao-total",
      "professionalMinScore": 180,
      "professionalScoreMetric": "xiqu-interprovincial-joint-exam",
      "rankUnavailable": true,
      "scoreOnly": true,
      "sourceId": "official-fujian-control-lines-2026",
      "sourceQuality": "official-fujian-control-line-image-verified",
      "sourceUrl": "https://www.eeafj.cn/gkptgkgsgg/20260624/14697.html",
      "formalScoreScope": "special-path-only",
      "controlLineRouteKind": "art",
      "controlLineKind": "戏曲类录取控制分数线",
      "controlLineSection": "高职（专科）",
      "cautions": [
        "这是福建省2026年特殊类型、艺术类或体育类控制线，不适用于普通类考生直接推荐。",
        "文化课分与专业统考或省际联考分是两个必须分别达到的门槛，不得相加或互相替代。",
        "控制线不是具体院校专业组、院校或专业的实际投档录取线。"
      ],
      "sourceFile": "data/admissions/raw/official-fujian-control-lines-2026/control-lines.jpg",
      "sourcePublishedAt": "2026-06-24"
    },
    {
      "id": "2026-fujian-control-0a3b5f75f123afe733",
      "province": "福建",
      "year": 2026,
      "subjectType": "艺术类（历史科目组）",
      "batch": "音乐教育类、戏剧影视导演类、播音与主持类、美术与设计类、书法类本科录取控制分数线",
      "schoolName": "福建省2026年普通高考录取控制分数线公布",
      "schoolTags": [
        "福建官方控制线",
        "特殊路径",
        "音乐教育类、戏剧影视导演类、播音与主持类、美术与设计类、书法类",
        "本科"
      ],
      "city": "福建",
      "dataType": "control-line",
      "majorName": "音乐教育类、戏剧影视导演类、播音与主持类、美术与设计类、书法类本科录取控制分数线",
      "majorGroup": "音乐教育类、戏剧影视导演类、播音与主持类、美术与设计类、书法类",
      "minScore": 344,
      "cultureScoreLine": 344,
      "scoreDimension": "culture-score",
      "scoreBasis": "gaokao-total",
      "professionalMinScore": 195,
      "professionalScoreMetric": "professional-unified-exam",
      "rankUnavailable": true,
      "scoreOnly": true,
      "sourceId": "official-fujian-control-lines-2026",
      "sourceQuality": "official-fujian-control-line-image-verified",
      "sourceUrl": "https://www.eeafj.cn/gkptgkgsgg/20260624/14697.html",
      "formalScoreScope": "special-path-only",
      "controlLineRouteKind": "art",
      "controlLineKind": "音乐教育类、戏剧影视导演类、播音与主持类、美术与设计类、书法类录取控制分数线",
      "controlLineSection": "本科",
      "cautions": [
        "这是福建省2026年特殊类型、艺术类或体育类控制线，不适用于普通类考生直接推荐。",
        "文化课分与专业统考或省际联考分是两个必须分别达到的门槛，不得相加或互相替代。",
        "控制线不是具体院校专业组、院校或专业的实际投档录取线。"
      ],
      "sourceFile": "data/admissions/raw/official-fujian-control-lines-2026/control-lines.jpg",
      "sourcePublishedAt": "2026-06-24"
    },
    {
      "id": "2026-fujian-control-de0d2a5e0f4d68dbd7",
      "province": "福建",
      "year": 2026,
      "subjectType": "艺术类（历史科目组）",
      "batch": "音乐教育类、戏剧影视导演类、播音与主持类、美术与设计类、书法类高职（专科）录取控制分数线",
      "schoolName": "福建省2026年普通高考录取控制分数线公布",
      "schoolTags": [
        "福建官方控制线",
        "特殊路径",
        "音乐教育类、戏剧影视导演类、播音与主持类、美术与设计类、书法类",
        "高职（专科）"
      ],
      "city": "福建",
      "dataType": "control-line",
      "majorName": "音乐教育类、戏剧影视导演类、播音与主持类、美术与设计类、书法类高职（专科）录取控制分数线",
      "majorGroup": "音乐教育类、戏剧影视导演类、播音与主持类、美术与设计类、书法类",
      "minScore": 165,
      "cultureScoreLine": 165,
      "scoreDimension": "culture-score",
      "scoreBasis": "gaokao-total",
      "professionalMinScore": 180,
      "professionalScoreMetric": "professional-unified-exam",
      "rankUnavailable": true,
      "scoreOnly": true,
      "sourceId": "official-fujian-control-lines-2026",
      "sourceQuality": "official-fujian-control-line-image-verified",
      "sourceUrl": "https://www.eeafj.cn/gkptgkgsgg/20260624/14697.html",
      "formalScoreScope": "special-path-only",
      "controlLineRouteKind": "art",
      "controlLineKind": "音乐教育类、戏剧影视导演类、播音与主持类、美术与设计类、书法类录取控制分数线",
      "controlLineSection": "高职（专科）",
      "cautions": [
        "这是福建省2026年特殊类型、艺术类或体育类控制线，不适用于普通类考生直接推荐。",
        "文化课分与专业统考或省际联考分是两个必须分别达到的门槛，不得相加或互相替代。",
        "控制线不是具体院校专业组、院校或专业的实际投档录取线。"
      ],
      "sourceFile": "data/admissions/raw/official-fujian-control-lines-2026/control-lines.jpg",
      "sourcePublishedAt": "2026-06-24"
    },
    {
      "id": "2026-fujian-control-cec802a190f8334bd1",
      "province": "福建",
      "year": 2026,
      "subjectType": "艺术类（历史科目组）",
      "batch": "音乐表演类、戏剧影视表演类、服装表演类、舞蹈类本科录取控制分数线",
      "schoolName": "福建省2026年普通高考录取控制分数线公布",
      "schoolTags": [
        "福建官方控制线",
        "特殊路径",
        "音乐表演类、戏剧影视表演类、服装表演类、舞蹈类",
        "本科"
      ],
      "city": "福建",
      "dataType": "control-line",
      "majorName": "音乐表演类、戏剧影视表演类、服装表演类、舞蹈类本科录取控制分数线",
      "majorGroup": "音乐表演类、戏剧影视表演类、服装表演类、舞蹈类",
      "minScore": 321,
      "cultureScoreLine": 321,
      "scoreDimension": "culture-score",
      "scoreBasis": "gaokao-total",
      "professionalMinScore": 195,
      "professionalScoreMetric": "professional-unified-exam",
      "rankUnavailable": true,
      "scoreOnly": true,
      "sourceId": "official-fujian-control-lines-2026",
      "sourceQuality": "official-fujian-control-line-image-verified",
      "sourceUrl": "https://www.eeafj.cn/gkptgkgsgg/20260624/14697.html",
      "formalScoreScope": "special-path-only",
      "controlLineRouteKind": "art",
      "controlLineKind": "音乐表演类、戏剧影视表演类、服装表演类、舞蹈类录取控制分数线",
      "controlLineSection": "本科",
      "cautions": [
        "这是福建省2026年特殊类型、艺术类或体育类控制线，不适用于普通类考生直接推荐。",
        "文化课分与专业统考或省际联考分是两个必须分别达到的门槛，不得相加或互相替代。",
        "控制线不是具体院校专业组、院校或专业的实际投档录取线。"
      ],
      "sourceFile": "data/admissions/raw/official-fujian-control-lines-2026/control-lines.jpg",
      "sourcePublishedAt": "2026-06-24"
    },
    {
      "id": "2026-fujian-control-f44856b8ca019d8b95",
      "province": "福建",
      "year": 2026,
      "subjectType": "艺术类（历史科目组）",
      "batch": "音乐表演类、戏剧影视表演类、服装表演类、舞蹈类高职（专科）录取控制分数线",
      "schoolName": "福建省2026年普通高考录取控制分数线公布",
      "schoolTags": [
        "福建官方控制线",
        "特殊路径",
        "音乐表演类、戏剧影视表演类、服装表演类、舞蹈类",
        "高职（专科）"
      ],
      "city": "福建",
      "dataType": "control-line",
      "majorName": "音乐表演类、戏剧影视表演类、服装表演类、舞蹈类高职（专科）录取控制分数线",
      "majorGroup": "音乐表演类、戏剧影视表演类、服装表演类、舞蹈类",
      "minScore": 165,
      "cultureScoreLine": 165,
      "scoreDimension": "culture-score",
      "scoreBasis": "gaokao-total",
      "professionalMinScore": 180,
      "professionalScoreMetric": "professional-unified-exam",
      "rankUnavailable": true,
      "scoreOnly": true,
      "sourceId": "official-fujian-control-lines-2026",
      "sourceQuality": "official-fujian-control-line-image-verified",
      "sourceUrl": "https://www.eeafj.cn/gkptgkgsgg/20260624/14697.html",
      "formalScoreScope": "special-path-only",
      "controlLineRouteKind": "art",
      "controlLineKind": "音乐表演类、戏剧影视表演类、服装表演类、舞蹈类录取控制分数线",
      "controlLineSection": "高职（专科）",
      "cautions": [
        "这是福建省2026年特殊类型、艺术类或体育类控制线，不适用于普通类考生直接推荐。",
        "文化课分与专业统考或省际联考分是两个必须分别达到的门槛，不得相加或互相替代。",
        "控制线不是具体院校专业组、院校或专业的实际投档录取线。"
      ],
      "sourceFile": "data/admissions/raw/official-fujian-control-lines-2026/control-lines.jpg",
      "sourcePublishedAt": "2026-06-24"
    },
    {
      "id": "2026-fujian-control-8a865d71c8b2e7da56",
      "province": "福建",
      "year": 2026,
      "subjectType": "艺术类（历史科目组）",
      "batch": "戏曲类本科录取控制分数线",
      "schoolName": "福建省2026年普通高考录取控制分数线公布",
      "schoolTags": [
        "福建官方控制线",
        "特殊路径",
        "戏曲类",
        "本科"
      ],
      "city": "福建",
      "dataType": "control-line",
      "majorName": "戏曲类本科录取控制分数线",
      "majorGroup": "戏曲类",
      "minScore": 321,
      "cultureScoreLine": 321,
      "scoreDimension": "culture-score",
      "scoreBasis": "gaokao-total",
      "professionalMinScore": 180,
      "professionalScoreMetric": "xiqu-interprovincial-joint-exam",
      "rankUnavailable": true,
      "scoreOnly": true,
      "sourceId": "official-fujian-control-lines-2026",
      "sourceQuality": "official-fujian-control-line-image-verified",
      "sourceUrl": "https://www.eeafj.cn/gkptgkgsgg/20260624/14697.html",
      "formalScoreScope": "special-path-only",
      "controlLineRouteKind": "art",
      "controlLineKind": "戏曲类录取控制分数线",
      "controlLineSection": "本科",
      "cautions": [
        "这是福建省2026年特殊类型、艺术类或体育类控制线，不适用于普通类考生直接推荐。",
        "文化课分与专业统考或省际联考分是两个必须分别达到的门槛，不得相加或互相替代。",
        "控制线不是具体院校专业组、院校或专业的实际投档录取线。"
      ],
      "sourceFile": "data/admissions/raw/official-fujian-control-lines-2026/control-lines.jpg",
      "sourcePublishedAt": "2026-06-24"
    },
    {
      "id": "2026-fujian-control-04c1860d8d9f66fe86",
      "province": "福建",
      "year": 2026,
      "subjectType": "艺术类（历史科目组）",
      "batch": "戏曲类高职（专科）录取控制分数线",
      "schoolName": "福建省2026年普通高考录取控制分数线公布",
      "schoolTags": [
        "福建官方控制线",
        "特殊路径",
        "戏曲类",
        "高职（专科）"
      ],
      "city": "福建",
      "dataType": "control-line",
      "majorName": "戏曲类高职（专科）录取控制分数线",
      "majorGroup": "戏曲类",
      "minScore": 165,
      "cultureScoreLine": 165,
      "scoreDimension": "culture-score",
      "scoreBasis": "gaokao-total",
      "professionalMinScore": 180,
      "professionalScoreMetric": "xiqu-interprovincial-joint-exam",
      "rankUnavailable": true,
      "scoreOnly": true,
      "sourceId": "official-fujian-control-lines-2026",
      "sourceQuality": "official-fujian-control-line-image-verified",
      "sourceUrl": "https://www.eeafj.cn/gkptgkgsgg/20260624/14697.html",
      "formalScoreScope": "special-path-only",
      "controlLineRouteKind": "art",
      "controlLineKind": "戏曲类录取控制分数线",
      "controlLineSection": "高职（专科）",
      "cautions": [
        "这是福建省2026年特殊类型、艺术类或体育类控制线，不适用于普通类考生直接推荐。",
        "文化课分与专业统考或省际联考分是两个必须分别达到的门槛，不得相加或互相替代。",
        "控制线不是具体院校专业组、院校或专业的实际投档录取线。"
      ],
      "sourceFile": "data/admissions/raw/official-fujian-control-lines-2026/control-lines.jpg",
      "sourcePublishedAt": "2026-06-24"
    },
    {
      "id": "2026-fujian-control-4e80fa1305febc1dbe",
      "province": "福建",
      "year": 2026,
      "subjectType": "体育类（物理科目组）",
      "batch": "体育类本科录取控制分数线",
      "schoolName": "福建省2026年普通高考录取控制分数线公布",
      "schoolTags": [
        "福建官方控制线",
        "特殊路径",
        "体育类",
        "本科"
      ],
      "city": "福建",
      "dataType": "control-line",
      "majorName": "体育类本科录取控制分数线",
      "majorGroup": "体育类",
      "minScore": 290,
      "cultureScoreLine": 290,
      "scoreDimension": "culture-score",
      "scoreBasis": "gaokao-total",
      "professionalMinScore": 60,
      "professionalScoreMetric": "professional-unified-exam",
      "rankUnavailable": true,
      "scoreOnly": true,
      "sourceId": "official-fujian-control-lines-2026",
      "sourceQuality": "official-fujian-control-line-image-verified",
      "sourceUrl": "https://www.eeafj.cn/gkptgkgsgg/20260624/14697.html",
      "formalScoreScope": "special-path-only",
      "controlLineRouteKind": "sports",
      "controlLineKind": "体育类录取控制分数线",
      "controlLineSection": "本科",
      "cautions": [
        "这是福建省2026年特殊类型、艺术类或体育类控制线，不适用于普通类考生直接推荐。",
        "文化课分与专业统考或省际联考分是两个必须分别达到的门槛，不得相加或互相替代。",
        "控制线不是具体院校专业组、院校或专业的实际投档录取线。"
      ],
      "sourceFile": "data/admissions/raw/official-fujian-control-lines-2026/control-lines.jpg",
      "sourcePublishedAt": "2026-06-24"
    },
    {
      "id": "2026-fujian-control-a0f86f0d87fbe4e1dc",
      "province": "福建",
      "year": 2026,
      "subjectType": "体育类（物理科目组）",
      "batch": "体育类高职（专科）录取控制分数线",
      "schoolName": "福建省2026年普通高考录取控制分数线公布",
      "schoolTags": [
        "福建官方控制线",
        "特殊路径",
        "体育类",
        "高职（专科）"
      ],
      "city": "福建",
      "dataType": "control-line",
      "majorName": "体育类高职（专科）录取控制分数线",
      "majorGroup": "体育类",
      "minScore": 165,
      "cultureScoreLine": 165,
      "scoreDimension": "culture-score",
      "scoreBasis": "gaokao-total",
      "professionalMinScore": 60,
      "professionalScoreMetric": "professional-unified-exam",
      "rankUnavailable": true,
      "scoreOnly": true,
      "sourceId": "official-fujian-control-lines-2026",
      "sourceQuality": "official-fujian-control-line-image-verified",
      "sourceUrl": "https://www.eeafj.cn/gkptgkgsgg/20260624/14697.html",
      "formalScoreScope": "special-path-only",
      "controlLineRouteKind": "sports",
      "controlLineKind": "体育类录取控制分数线",
      "controlLineSection": "高职（专科）",
      "cautions": [
        "这是福建省2026年特殊类型、艺术类或体育类控制线，不适用于普通类考生直接推荐。",
        "文化课分与专业统考或省际联考分是两个必须分别达到的门槛，不得相加或互相替代。",
        "控制线不是具体院校专业组、院校或专业的实际投档录取线。"
      ],
      "sourceFile": "data/admissions/raw/official-fujian-control-lines-2026/control-lines.jpg",
      "sourcePublishedAt": "2026-06-24"
    },
    {
      "id": "2026-fujian-control-7689b5f0072f7d3109",
      "province": "福建",
      "year": 2026,
      "subjectType": "体育类（历史科目组）",
      "batch": "体育类本科录取控制分数线",
      "schoolName": "福建省2026年普通高考录取控制分数线公布",
      "schoolTags": [
        "福建官方控制线",
        "特殊路径",
        "体育类",
        "本科"
      ],
      "city": "福建",
      "dataType": "control-line",
      "majorName": "体育类本科录取控制分数线",
      "majorGroup": "体育类",
      "minScore": 298,
      "cultureScoreLine": 298,
      "scoreDimension": "culture-score",
      "scoreBasis": "gaokao-total",
      "professionalMinScore": 60,
      "professionalScoreMetric": "professional-unified-exam",
      "rankUnavailable": true,
      "scoreOnly": true,
      "sourceId": "official-fujian-control-lines-2026",
      "sourceQuality": "official-fujian-control-line-image-verified",
      "sourceUrl": "https://www.eeafj.cn/gkptgkgsgg/20260624/14697.html",
      "formalScoreScope": "special-path-only",
      "controlLineRouteKind": "sports",
      "controlLineKind": "体育类录取控制分数线",
      "controlLineSection": "本科",
      "cautions": [
        "这是福建省2026年特殊类型、艺术类或体育类控制线，不适用于普通类考生直接推荐。",
        "文化课分与专业统考或省际联考分是两个必须分别达到的门槛，不得相加或互相替代。",
        "控制线不是具体院校专业组、院校或专业的实际投档录取线。"
      ],
      "sourceFile": "data/admissions/raw/official-fujian-control-lines-2026/control-lines.jpg",
      "sourcePublishedAt": "2026-06-24"
    },
    {
      "id": "2026-fujian-control-f093f997cd15922c70",
      "province": "福建",
      "year": 2026,
      "subjectType": "体育类（历史科目组）",
      "batch": "体育类高职（专科）录取控制分数线",
      "schoolName": "福建省2026年普通高考录取控制分数线公布",
      "schoolTags": [
        "福建官方控制线",
        "特殊路径",
        "体育类",
        "高职（专科）"
      ],
      "city": "福建",
      "dataType": "control-line",
      "majorName": "体育类高职（专科）录取控制分数线",
      "majorGroup": "体育类",
      "minScore": 165,
      "cultureScoreLine": 165,
      "scoreDimension": "culture-score",
      "scoreBasis": "gaokao-total",
      "professionalMinScore": 60,
      "professionalScoreMetric": "professional-unified-exam",
      "rankUnavailable": true,
      "scoreOnly": true,
      "sourceId": "official-fujian-control-lines-2026",
      "sourceQuality": "official-fujian-control-line-image-verified",
      "sourceUrl": "https://www.eeafj.cn/gkptgkgsgg/20260624/14697.html",
      "formalScoreScope": "special-path-only",
      "controlLineRouteKind": "sports",
      "controlLineKind": "体育类录取控制分数线",
      "controlLineSection": "高职（专科）",
      "cautions": [
        "这是福建省2026年特殊类型、艺术类或体育类控制线，不适用于普通类考生直接推荐。",
        "文化课分与专业统考或省际联考分是两个必须分别达到的门槛，不得相加或互相替代。",
        "控制线不是具体院校专业组、院校或专业的实际投档录取线。"
      ],
      "sourceFile": "data/admissions/raw/official-fujian-control-lines-2026/control-lines.jpg",
      "sourcePublishedAt": "2026-06-24"
    }
  ],
  "diagnostics": {
    "recordCount": 22,
    "ordinaryRecords": 4,
    "specialPathRecords": 18,
    "cultureProfessionalRecords": 16,
    "routeCounts": {
      "ordinary-bachelor": 2,
      "ordinary-vocational": 2,
      "special": 2,
      "art": 12,
      "sports": 4
    },
    "ordinaryBoundaries": {
      "物理类": {
        "bachelor": 446,
        "vocational": 235
      },
      "历史类": {
        "bachelor": 458,
        "vocational": 235
      }
    },
    "professionalMetricCounts": {
      "professional-unified-exam": 12,
      "xiqu-interprovincial-joint-exam": 4
    }
  }
}
